Workbook

Sheet Painel
A3: Quant.
A4: Status | B4: Total
A5: Em Desenvolvimento | B5: 6
A6: Entregue | B6: 95
A7: Backlog | B7: 21
A8: Paralisado | B8: 2
A9: QA | B9: 3
A10: Removido | B10: 1
A11: Total Geral | B11: 128

Sheet Melhorias Funil (Capa)
N1: TI | R1: GUT
B2: ID | C2: Data da Inserção | D2: Solicitante | E2: Área | F2: Chamado | G2: Squad | H2: Status | I2: Avaliação área de Negocio | J2: Classificação área | K2: Resumo Melhoria | L2: Descrição | M2: OBS | N2: Tamanho | O2: Comitê de TI | P2: Squad On Going | Q2: Nº Azure | R2: Gravidade | S2: Urgência | T2: Tendência | U2: Resultado GUT | V2: Prioridade
B3: ='LIVRE Oficial'!A1 -> ID | C3: ='LIVRE Oficial'!B2 -> 45758 | D3: ='LIVRE Oficial'!C2 -> Daniela Mochon | E3: ='LIVRE Oficial'!D2 -> Comercial | F3: ='LIVRE Oficial'!E2 -> 0 | G3: ='LIVRE Oficial'!I2 -> Funil | H3: ='LIVRE Oficial'!F2 -> Entregue | I3: ='LIVRE Oficial'!G2 -> 3 | J3: ='LIVRE Oficial'!H2 -> Melhoria | K3: ='LIVRE Oficial'!L2 -> LEAD | Distribuição Automática e Inteligente de Leads no Salesforce (Vendedores Internos) | L3: ='LIVRE Oficial'!V2 -> 0 | M3: ='LIVRE Oficial'!U2 -> 0 | N3: ='LIVRE Oficial'!M2 -> G | O3: ='LIVRE Oficial'!N2 -> FALSE | P3: ='LIVRE Oficial'!O2 -> FALSE | Q3: ='LIVRE Oficial'!J2 -> 364684 | R3: ='LIVRE Oficial'!P2 -> 1 | S3: ='LIVRE Oficial'!Q2 -> 2 | T3: ='LIVRE Oficial'!R2 -> 3 | U3: ='LIVRE Oficial'!S2 -> 6 | V3: ='LIVRE Oficial'!K2 -> 1
B4: ='LIVRE Oficial'!A2 -> 1 | C4: ='LIVRE Oficial'!B3 -> 46171 | D4: ='LIVRE Oficial'!C3 -> Daniela Mochon | E4: ='LIVRE Oficial'!D3 -> Comercial | F4: ='LIVRE Oficial'!E3 -> 0 | G4: ='LIVRE Oficial'!I3 -> Funil | H4: ='LIVRE Oficial'!F3 -> Aguardando Refinamento de Negócio | I4: ='LIVRE Oficial'!G3 -> 1 | J4: ='LIVRE Oficial'!H3 -> Melhoria | K4: ='LIVRE Oficial'!L3 -> LEAD | Criação do campo “LeadPrincipalCPF” | L4: ='LIVRE Oficial'!V3 -> 0 | M4: ='LIVRE Oficial'!U3 -> 0 | N4: ='LIVRE Oficial'!M3 -> P | O4: ='LIVRE Oficial'!N3 -> 0 | P4: ='LIVRE Oficial'!O3 -> TRUE | Q4: ='LIVRE Oficial'!J3 -> 679614 | R4: ='LIVRE Oficial'!P3 -> 0 | S4: ='LIVRE Oficial'!Q3 -> 0 | T4: ='LIVRE Oficial'!R3 -> 0 | U4: ='LIVRE Oficial'!S3 -> 0 | V4: ='LIVRE Oficial'!K3 -> 4
B5: ='LIVRE Oficial'!A3 -> 131 | C5: ='LIVRE Oficial'!B4 -> 46238 | D5: ='LIVRE Oficial'!C4 -> Daniela Mochon | E5: ='LIVRE Oficial'!D4 -> Comercial | F5: ='LIVRE Oficial'!E4 -> 0 | G5: ='LIVRE Oficial'!I4 -> Funil | H5: ='LIVRE Oficial'!F4 -> Backlog | I5: ='LIVRE Oficial'!G4 -> 3 | J5: ='LIVRE Oficial'!H4 -> Melhoria | K5: ='LIVRE Oficial'!L4 -> CONTRATO | Atualizar automaticamente status e dados de contratos e pedidos via integração entre Salesforce e Locavia | L5: ='LIVRE Oficial'!V4 -> 0 | M5: ='LIVRE Oficial'!U4 -> 0 | N5: ='LIVRE Oficial'!M4 -> GG | O5: ='LIVRE Oficial'!N4 -> TRUE | P5: ='LIVRE Oficial'!O4 -> 0 | Q5: ='LIVRE Oficial'!J4 -> 539582 | R5: ='LIVRE Oficial'!P4 -> 3 | S5: ='LIVRE Oficial'!Q4 -> 2 | T5: ='LIVRE Oficial'!R4 -> 3 | U5: ='LIVRE Oficial'!S4 -> 8 | V5: ='LIVRE Oficial'!K4 -> 0
B6: ='LIVRE Oficial'!A4 -> 27 | C6: ='LIVRE Oficial'!B5 -> 45754 | D6: ='LIVRE Oficial'!C5 -> Daniela Mochon | E6: ='LIVRE Oficial'!D5 -> Comercial | F6: ='LIVRE Oficial'!E5 -> 0 | G6: ='LIVRE Oficial'!I5 -> Funil | H6: ='LIVRE Oficial'!F5 -> Entregue | I6: ='LIVRE Oficial'!G5 | J6: ='LIVRE Oficial'!H5 -> Melhoria | K6: ='LIVRE Oficial'!L5 -> ATLAS | Remover a limitação de 150 propostas na exibição com filtros de Status aplicados em "Minhas propostas" | L6: ='LIVRE Oficial'!V5 -> 0 | M6: ='LIVRE Oficial'!U5 -> 0 | N6: ='LIVRE Oficial'!M5 -> 0 | Q6: ='LIVRE Oficial'!J5 -> 312387 | R6: ='LIVRE Oficial'!P5 | S6: ='LIVRE Oficial'!Q5 | T6: ='LIVRE Oficial'!R5 | U6: ='LIVRE Oficial'!S5 -> #VALUE! | V6: ='LIVRE Oficial'!K5
B7: ='LIVRE Oficial'!A5 -> 4 | C7: ='LIVRE Oficial'!B6 -> 9609 | D7: ='LIVRE Oficial'!C6 -> Daniela Mochon | E7: ='LIVRE Oficial'!D6 -> Comercial | F7: ='LIVRE Oficial'!E6 -> C2604-24461 | G7: ='LIVRE Oficial'!I6 -> Funil | H7: ='LIVRE Oficial'!F6 -> Entregue | I7: ='LIVRE Oficial'!G6 -> 1 | J7: ='LIVRE Oficial'!H6 -> BUG | K7: ='LIVRE Oficial'!L6 -> CONTA | Permitir alteração manual do nome da Conta para registros criados de forma sistêmica | L7: ='LIVRE Oficial'!V6 -> 0 | M7: ='LIVRE Oficial'!U6 -> 0 | N7: ='LIVRE Oficial'!M6 -> 0 | Q7: ='LIVRE Oficial'!J6 -> 593226 | R7: ='LIVRE Oficial'!P6 -> 1 | S7: ='LIVRE Oficial'!Q6 -> 3 | T7: ='LIVRE Oficial'!R6 -> 3 | U7: ='LIVRE Oficial'!S6 -> 7 | V7: ='LIVRE Oficial'!K6 -> 9
B8: ='LIVRE Oficial'!A6 -> 5 | C8: ='LIVRE Oficial'!B7 -> 9454 | D8: ='LIVRE Oficial'!C7 -> Daniela Mochon | E8: ='LIVRE Oficial'!D7 -> Comercial | F8: ='LIVRE Oficial'!E7 -> 0 | G8: ='LIVRE Oficial'!I7 -> Funil | H8: ='LIVRE Oficial'!F7 -> Entregue | I8: ='LIVRE Oficial'!G7 -> 3 | J8: ='LIVRE Oficial'!H7 -> Melhoria | K8: ='LIVRE Oficial'!L7 -> OPORTUNIDADE | Criação de Nova Oportunidade a partir de Fechamento da Op de Renovação | L8: ='LIVRE Oficial'!V7 -> 0 | M8: ='LIVRE Oficial'!U7 -> 0 | N8: ='LIVRE Oficial'!M7 -> 0 | Q8: ='LIVRE Oficial'!J7 -> 371328 | R8: ='LIVRE Oficial'!P7 -> 3 | S8: ='LIVRE Oficial'!Q7 -> 3 | T8: ='LIVRE Oficial'!R7 -> 3 | U8: ='LIVRE Oficial'!S7 -> 9 | V8: ='LIVRE Oficial'!K7 -> 4
B9: ='LIVRE Oficial'!A7 -> 6 | C9: ='LIVRE Oficial'!B8 -> 9616 | D9: ='LIVRE Oficial'!C8 -> Pedro Henrique | E9: ='LIVRE Oficial'!D8 -> Comercial | F9: ='LIVRE Oficial'!E8 -> C2604-17343 | G9: ='LIVRE Oficial'!I8 -> Funil | H9: ='LIVRE Oficial'!F8 -> Entregue | I9: ='LIVRE Oficial'!G8 -> 1 | J9: ='LIVRE Oficial'!H8 -> BUG | K9: ='LIVRE Oficial'!L8 -> OPORTUNIDADE | Desenvolver Correção do Status da Análise de Crédito | L9: ='LIVRE Oficial'!V8 -> 0 | M9: ='LIVRE Oficial'!U8 -> 0 | N9: ='LIVRE Oficial'!M8 -> 0 | Q9: ='LIVRE Oficial'!J8 -> 625264 | R9: ='LIVRE Oficial'!P8 -> 2 | S9: ='LIVRE Oficial'!Q8 -> 1 | T9: ='LIVRE Oficial'!R8 -> 2 | U9: ='LIVRE Oficial'!S8 -> 5 | V9: ='LIVRE Oficial'!K8 -> 13
B10: ='LIVRE Oficial'!A8 -> 7 | C10: ='LIVRE Oficial'!B9 -> 9614 | D10: ='LIVRE Oficial'!C9 -> Monique Evelin | E10: ='LIVRE Oficial'!D9 -> Crédito | F10: ='LIVRE Oficial'!E9 -> 0 | G10: ='LIVRE Oficial'!I9 -> Funil | H10: ='LIVRE Oficial'!F9 -> Entregue | I10: ='LIVRE Oficial'!G9 -> 1 | J10: ='LIVRE Oficial'!H9 -> Melhoria | K10: ='LIVRE Oficial'!L9 -> CONTA | Botão Manual para Consulta SERASA na Conta (Pessoa Física) | L10: ='LIVRE Oficial'!V9 -> 0 | M10: ='LIVRE Oficial'!U9 -> 0 | N10: ='LIVRE Oficial'!M9 -> M | Q10: ='LIVRE Oficial'!J9 -> 625328 | R10: ='LIVRE Oficial'!P9 -> 1 | S10: ='LIVRE Oficial'!Q9 -> 1 | T10: ='LIVRE Oficial'!R9 -> 1 | U10: ='LIVRE Oficial'!S9 -> 3 | V10: ='LIVRE Oficial'!K9 -> 22
B11: ='LIVRE Oficial'!A9 -> 8 | C11: ='LIVRE Oficial'!B10 -> 9551 | D11: ='LIVRE Oficial'!C10 -> Daniela Mochon | E11: ='LIVRE Oficial'!D10 -> Comercial | F11: ='LIVRE Oficial'!E10 -> 0 | G11: ='LIVRE Oficial'!I10 -> Funil | H11: ='LIVRE Oficial'!F10 -> Entregue | I11: ='LIVRE Oficial'!G10 -> 1 | J11: ='LIVRE Oficial'!H10 -> Melhoria | K11: ='LIVRE Oficial'!L10 -> QUOTE | Desenvolver envio de Opcionais no Pedido de Compra para o Locavia | L11: ='LIVRE Oficial'!V10 -> 0 | M11: ='LIVRE Oficial'!U10 -> 0 | N11: ='LIVRE Oficial'!M10 -> M | Q11: ='LIVRE Oficial'!J10 -> 397306 | R11: ='LIVRE Oficial'!P10 -> 2 | S11: ='LIVRE Oficial'!Q10 -> 2 | T11: ='LIVRE Oficial'!R10 -> 1 | U11: ='LIVRE Oficial'!S10 -> 5 | V11: ='LIVRE Oficial'!K10 -> 2
B12: ='LIVRE Oficial'!A10 -> 9 | C12: ='LIVRE Oficial'!B11 -> 46269 | D12: ='LIVRE Oficial'!C11 -> Daniela Mochon | E12: ='LIVRE Oficial'!D11 -> Comercial | F12: ='LIVRE Oficial'!E11 -> 0 | G12: ='LIVRE Oficial'!I11 -> Funil | H12: ='LIVRE Oficial'!F11 -> Entregue | I12: ='LIVRE Oficial'!G11 -> 1 | J12: ='LIVRE Oficial'!H11 -> BUG | K12: ='LIVRE Oficial'!L11 -> OPORTUNIDADE | Desenvolver correção para atualização do motivo do pedido de compra em cenários de renovação | L12: ='LIVRE Oficial'!V11 -> 0 | M12: ='LIVRE Oficial'!U11 -> 0 | N12: ='LIVRE Oficial'!M11 -> P | Q12: ='LIVRE Oficial'!J11 -> 543229 | R12: ='LIVRE Oficial'!P11 -> 1 | S12: ='LIVRE Oficial'!Q11 -> 1 | T12: ='LIVRE Oficial'!R11 -> 1 | U12: ='LIVRE Oficial'!S11 -> 3 | V12: ='LIVRE Oficial'!K11 -> 21
B13: ='LIVRE Oficial'!A11 -> 10 | C13: ='LIVRE Oficial'!B12 -> 46269 | D13: ='LIVRE Oficial'!C12 -> Daniela Mochon | E13: ='LIVRE Oficial'!D12 -> Comercial | F13: ='LIVRE Oficial'!E12 -> 0 | G13: ='LIVRE Oficial'!I12 -> Funil | H13: ='LIVRE Oficial'!F12 -> Entregue | I13: ='LIVRE Oficial'!G12 -> 1 | J13: ='LIVRE Oficial'!H12 -> Melhoria | K13: ='LIVRE Oficial'!L12 -> OPORTUNIDADE | Permitir geração de pedido de compra sem delay de 8 dias para casos de retenção de clientes | L13: ='LIVRE Oficial'!V12 -> 0 | M13: ='LIVRE Oficial'!U12 -> 0 | N13: ='LIVRE Oficial'!M12 -> M | Q13: ='LIVRE Oficial'!J12 -> 543196 | R13: ='LIVRE Oficial'!P12 -> 2 | S13: ='LIVRE Oficial'!Q12 -> 2 | T13: ='LIVRE Oficial'!R12 -> 1 | U13: ='LIVRE Oficial'!S12 -> 5 | V13: ='LIVRE Oficial'!K12 -> 14
B14: ='LIVRE Oficial'!A12 -> 11 | C14: ='LIVRE Oficial'!B13 -> 46170 | D14: ='LIVRE Oficial'!C13 -> Daniela Mochon | E14: ='LIVRE Oficial'!D13 -> Comercial | F14: ='LIVRE Oficial'!E13 -> 0 | G14: ='LIVRE Oficial'!I13 -> Funil | H14: ='LIVRE Oficial'!F13 -> Entregue | I14: ='LIVRE Oficial'!G13 -> 0 | J14: ='LIVRE Oficial'!H13 -> Melhoria | K14: ='LIVRE Oficial'!L13 -> CONTRATO | Criar campos de controle para integração de retorno de assinatura contrato (Authentique) | L14: ='LIVRE Oficial'!V13 -> 0 | M14: ='LIVRE Oficial'!U13 -> Fora do Escopo SPRINT 04 | N14: ='LIVRE Oficial'!M13 -> G | Q14: ='LIVRE Oficial'!J13 -> 660405 | R14: ='LIVRE Oficial'!P13 -> 1 | S14: ='LIVRE Oficial'!Q13 -> 1 | T14: ='LIVRE Oficial'!R13 -> 1 | U14: ='LIVRE Oficial'!S13 -> 3 | V14: ='LIVRE Oficial'!K13 -> 1
B15: ='LIVRE Oficial'!A13 -> 119 | C15: ='LIVRE Oficial'!B14 -> 9611 | D15: ='LIVRE Oficial'!C14 -> Proativo | E15: ='LIVRE Oficial'!D14 -> Funil | F15: ='LIVRE Oficial'!E14 -> 0 | G15: ='LIVRE Oficial'!I14 -> Funil | H15: ='LIVRE Oficial'!F14 -> Entregue | I15: ='LIVRE Oficial'!G14 | J15: ='LIVRE Oficial'!H14 -> BUG | K15: ='LIVRE Oficial'!L14 -> ASSET - Stauts do Ativo Fleet aparecendo no Livre | L15: ='LIVRE Oficial'!V14 -> 0 | M15: ='LIVRE Oficial'!U14 -> 0 | N15: ='LIVRE Oficial'!M14 -> 0 | Q15: ='LIVRE Oficial'!J14 -> 594558 | R15: ='LIVRE Oficial'!P14 | S15: ='LIVRE Oficial'!Q14 | T15: ='LIVRE Oficial'!R14 | U15: ='LIVRE Oficial'!S14 -> #VALUE! | V15: ='LIVRE Oficial'!K14
B16: ='LIVRE Oficial'!A14 -> 13 | C16: ='LIVRE Oficial'!B15 -> 46223 | D16: ='LIVRE Oficial'!C15 -> Jéssica Fachina | E16: ='LIVRE Oficial'!D15 -> Funil Crédito | F16: ='LIVRE Oficial'!E15 -> 0 | G16: ='LIVRE Oficial'!I15 -> Funil | H16: ='LIVRE Oficial'!F15 -> Entregue | I16: ='LIVRE Oficial'!G15 -> 0 | J16: ='LIVRE Oficial'!H15 -> Melhoria | K16: ='LIVRE Oficial'!L15 -> OPORTUNIDADE | Enviar novas informações da proposta de Renovação para a Plataforma de Crédito | L16: ='LIVRE Oficial'!V15 -> 0 | M16: ='LIVRE Oficial'!U15 -> 0 | N16: ='LIVRE Oficial'!M15 -> M | Q16: ='LIVRE Oficial'!J15 -> 706718 | R16: ='LIVRE Oficial'!P15 -> 0 | S16: ='LIVRE Oficial'!Q15 -> 0 | T16: ='LIVRE Oficial'!R15 -> 0 | U16: ='LIVRE Oficial'!S15 -> 0 | V16: ='LIVRE Oficial'!K15 -> 0
B17: ='LIVRE Oficial'!A15 -> 140 | C17: ='LIVRE Oficial'!B16 -> 46224 | D17: ='LIVRE Oficial'!C16 -> Jéssica Fachina | E17: ='LIVRE Oficial'!D16 -> Funil + Atlas | F17: ='LIVRE Oficial'!E16 -> 0 | G17: ='LIVRE Oficial'!I16 -> Funil + Atlas | H17: ='LIVRE Oficial'!F16 -> Entregue | I17: ='LIVRE Oficial'!G16 -> 0 | J17: ='LIVRE Oficial'!H16 -> Melhoria | K17: ='LIVRE Oficial'!L16 -> OPORTUNIDADE | Desenvolver novas regras de Desatrelamento V2 | L17: ='LIVRE Oficial'!V16 -> 0 | M17: ='LIVRE Oficial'!U16 -> 0 | N17: ='LIVRE Oficial'!M16 -> M | Q17: ='LIVRE Oficial'!J16 -> 706680 | R17: ='LIVRE Oficial'!P16 -> 0 | S17: ='LIVRE Oficial'!Q16 -> 0 | T17: ='LIVRE Oficial'!R16 -> 0 | U17: ='LIVRE Oficial'!S16 -> 0 | V17: ='LIVRE Oficial'!K16 -> 1
B18: ='LIVRE Oficial'!A16 -> 141 | C18: ='LIVRE Oficial'!#REF! -> #REF! | D18: ='LIVRE Oficial'!#REF! -> #REF! | E18: ='LIVRE Oficial'!#REF! -> #REF! | F18: ='LIVRE Oficial'!#REF! -> #REF! | G18: ='LIVRE Oficial'!#REF! -> #REF! | H18: ='LIVRE Oficial'!#REF! -> #REF! | I18: ='LIVRE Oficial'!#REF! -> #REF! | J18: ='LIVRE Oficial'!#REF! -> #REF! | ... N18: ='LIVRE Oficial'!#REF! -> #REF! | Q18: ='LIVRE Oficial'!#REF! -> #REF! | R18: ='LIVRE Oficial'!#REF! -> #REF! | S18: ='LIVRE Oficial'!#REF! -> #REF! | T18: ='LIVRE Oficial'!#REF! -> #REF! | U18: ='LIVRE Oficial'!#REF! -> #REF! | V18: ='LIVRE Oficial'!#REF! -> #REF!
B19: ='LIVRE Oficial'!#REF! -> #REF! | C19: ='LIVRE Oficial'!B18 -> 46174 | D19: ='LIVRE Oficial'!C18 -> Daniela Mochon | E19: ='LIVRE Oficial'!D18 -> Comercial | F19: ='LIVRE Oficial'!E18 -> 0 | G19: ='LIVRE Oficial'!I18 -> Funil | H19: ='LIVRE Oficial'!F18 -> Entregue | I19: ='LIVRE Oficial'!G18 -> 0 | J19: ='LIVRE Oficial'!H18 -> Melhoria | K19: ='LIVRE Oficial'!L18 -> OPORTUNIDADE | Desatrelamento Automático de Vendedor | L19: ='LIVRE Oficial'!V18 -> 0 | M19: ='LIVRE Oficial'!U18 -> 0 | N19: ='LIVRE Oficial'!M18 -> M | Q19: ='LIVRE Oficial'!J18 -> 661063 | R19: ='LIVRE Oficial'!P18 -> 0 | S19: ='LIVRE Oficial'!Q18 -> 0 | T19: ='LIVRE Oficial'!R18 -> 0 | U19: ='LIVRE Oficial'!S18 -> 0 | V19: ='LIVRE Oficial'!K18 -> 2
B20: ='LIVRE Oficial'!A18 -> 121 | C20: ='LIVRE Oficial'!B19 -> 46174 | D20: ='LIVRE Oficial'!C19 -> Daniela Mochon | E20: ='LIVRE Oficial'!D19 -> Comercial | F20: ='LIVRE Oficial'!E19 -> 0 | G20: ='LIVRE Oficial'!I19 -> Funil | H20: ='LIVRE Oficial'!F19 -> Entregue | I20: ='LIVRE Oficial'!G19 -> 0 | J20: ='LIVRE Oficial'!H19 -> BUG | K20: ='LIVRE Oficial'!L19 -> BUG | Nas trocas ou alterações de vendedor, apenas o ID é atualizado e as outras informações ficam incorretas | L20: ='LIVRE Oficial'!V19 -> 0 | M20: ='LIVRE Oficial'!U19 -> Sprint 8 | N20: ='LIVRE Oficial'!M19 -> P | Q20: ='LIVRE Oficial'!J19 -> - | R20: ='LIVRE Oficial'!P19 -> 0 | S20: ='LIVRE Oficial'!Q19 -> 0 | T20: ='LIVRE Oficial'!R19 -> 0 | U20: ='LIVRE Oficial'!S19 -> 0 | V20: ='LIVRE Oficial'!K19 -> 2
B21: ='LIVRE Oficial'!A19 -> 122 | C21: ='LIVRE Oficial'!B20 -> 46197 | D21: ='LIVRE Oficial'!C20 -> Daniela Mochon | E21: ='LIVRE Oficial'!D20 -> Comercial | F21: ='LIVRE Oficial'!E20 -> 0 | G21: ='LIVRE Oficial'!I20 -> Funil & Atlas | H21: ='LIVRE Oficial'!F20 -> Entregue | I21: ='LIVRE Oficial'!G20 -> 1 | J21: ='LIVRE Oficial'!H20 -> Melhoria | K21: ='LIVRE Oficial'!L20 -> OPORTUNIDADE | Adicionar campo de "Prazo de Entrega Informado ao cliente" | L21: ='LIVRE Oficial'!V20 -> 0 | M21: ='LIVRE Oficial'!U20 -> 0 | N21: ='LIVRE Oficial'!M20 -> P | Q21: ='LIVRE Oficial'!J20 -> 679043 | R21: ='LIVRE Oficial'!P20 -> 0 | S21: ='LIVRE Oficial'!Q20 -> 0 | T21: ='LIVRE Oficial'!R20 -> 0 | U21: ='LIVRE Oficial'!S20 -> 0 | V21: ='LIVRE Oficial'!K20 -> 0
B22: ='LIVRE Oficial'!A20 -> 0 | C22: ='LIVRE Oficial'!B21 -> 46238 | D22: ='LIVRE Oficial'!C21 -> Daniela Mochon | E22: ='LIVRE Oficial'!D21 -> Comercial | F22: ='LIVRE Oficial'!E21 -> 0 | G22: ='LIVRE Oficial'!I21 -> Funil | H22: ='LIVRE Oficial'!F21 -> Entregue | I22: ='LIVRE Oficial'!G21 -> 3 | J22: ='LIVRE Oficial'!H21 -> Melhoria | K22: ='LIVRE Oficial'!L21 -> OPORTUNIDADE | Garantir o envio e registro do desconto de 3% do Atlas para o Salesforce | L22: ='LIVRE Oficial'!V21 -> 0 | M22: ='LIVRE Oficial'!U21 -> Entregue a parte funcional e API do lado do SF. Aguardando Atlas | N22: ='LIVRE Oficial'!M21 -> 0 | Q22: ='LIVRE Oficial'!J21 -> 539594 | R22: ='LIVRE Oficial'!P21 -> 3 | S22: ='LIVRE Oficial'!Q21 -> 2 | T22: ='LIVRE Oficial'!R21 -> 3 | U22: ='LIVRE Oficial'!S21 -> 8 | V22: ='LIVRE Oficial'!K21 -> 5
B23: ='LIVRE Oficial'!A21 -> 25 | C23: ='LIVRE Oficial'!B22 -> 46210 | D23: ='LIVRE Oficial'!C22 -> Jéssica Fachina | E23: ='LIVRE Oficial'!D22 -> Comercial | F23: ='LIVRE Oficial'!E22 -> 0 | G23: ='LIVRE Oficial'!I22 -> Funil + Atlas | H23: ='LIVRE Oficial'!F22 -> Entregue | I23: ='LIVRE Oficial'!G22 -> 0 | J23: ='LIVRE Oficial'!H22 -> Melhoria | K23: ='LIVRE Oficial'!L22 -> LEAD | Encaminhar automaticamente para LOST Leads com Score inferior a 300 | L23: ='LIVRE Oficial'!V22 -> 0 | M23: ='LIVRE Oficial'!U22 -> 0 | N23: ='LIVRE Oficial'!M22 -> M | Q23: ='LIVRE Oficial'!J22 -> 706752 | R23: ='LIVRE Oficial'!P22 -> 0 | S23: ='LIVRE Oficial'!Q22 -> 0 | T23: ='LIVRE Oficial'!R22 -> 0 | U23: ='LIVRE Oficial'!S22 -> 0 | V23: ='LIVRE Oficial'!K22 -> 0
B24: ='LIVRE Oficial'!A22 -> 135 | C24: ='LIVRE Oficial'!B23 -> 46182 | D24: ='LIVRE Oficial'!C23 -> Daniela Mochon | E24: ='LIVRE Oficial'!D23 -> Comercial | F24: ='LIVRE Oficial'!E23 -> 0 | G24: ='LIVRE Oficial'!I23 -> Funil | H24: ='LIVRE Oficial'!F23 -> Entregue | I24: ='LIVRE Oficial'!G23 -> 0 | J24: ='LIVRE Oficial'!H23 -> Melhoria | K24: ='LIVRE Oficial'!L23 -> Enviar notificação ao vendedor quando um novo lead for distribuido a ele | L24: ='LIVRE Oficial'!V23 -> 0 | M24: ='LIVRE Oficial'!U23 -> 0 | N24: ='LIVRE Oficial'!M23 -> P | Q24: ='LIVRE Oficial'!J23 -> 670511 | R24: ='LIVRE Oficial'!P23 -> 0 | S24: ='LIVRE Oficial'!Q23 -> 0 | T24: ='LIVRE Oficial'!R23 -> 0 | U24: ='LIVRE Oficial'!S23 -> 0 | V24: ='LIVRE Oficial'!K23 -> 3
B25: ='LIVRE Oficial'!A23 -> 129 | C25: ='LIVRE Oficial'!B24 -> 9427 | D25: ='LIVRE Oficial'!C24 -> Daniela Mochon | E25: ='LIVRE Oficial'!D24 -> Comercial | F25: ='LIVRE Oficial'!E24 -> 0 | G25: ='LIVRE Oficial'!I24 -> Funil | H25: ='LIVRE Oficial'!F24 -> Backlog | I25: ='LIVRE Oficial'!G24 | J25: ='LIVRE Oficial'!H24 -> Melhoria | K25: ='LIVRE Oficial'!L24 -> LEAD | Serviço de Consulta de CEP do Funil de Vendas | L25: ='LIVRE Oficial'!V24 -> 0 | M25: ='LIVRE Oficial'!U24 -> 0 | N25: ='LIVRE Oficial'!M24 -> M | Q25: ='LIVRE Oficial'!J24 -> 358303 | R25: ='LIVRE Oficial'!P24 | S25: ='LIVRE Oficial'!Q24 | T25: ='LIVRE Oficial'!R24 | U25: ='LIVRE Oficial'!S24 -> #VALUE! | V25: ='LIVRE Oficial'!K24 -> 0
B26: ='LIVRE Oficial'!A24 -> 31 | C26: ='LIVRE Oficial'!B25 -> 9616 | D26: ='LIVRE Oficial'!C25 -> Daniela Mochon | E26: ='LIVRE Oficial'!D25 -> Comercial | F26: ='LIVRE Oficial'!E25 -> 0 | G26: ='LIVRE Oficial'!I25 -> Funil | H26: ='LIVRE Oficial'!F25 -> Entregue | I26: ='LIVRE Oficial'!G25 -> 1 | J26: ='LIVRE Oficial'!H25 -> Melhoria | K26: ='LIVRE Oficial'!L25 -> OPORTUNIDADE | Desenvolver Correção do Status da Análise de Crédito | L26: ='LIVRE Oficial'!V25 -> 0 | M26: ='LIVRE Oficial'!U25 -> 0 | N26: ='LIVRE Oficial'!M25 -> 0 | Q26: ='LIVRE Oficial'!J25 -> 625264 | R26: ='LIVRE Oficial'!P25 -> 2 | S26: ='LIVRE Oficial'!Q25 -> 1 | T26: ='LIVRE Oficial'!R25 -> 2 | U26: ='LIVRE Oficial'!S25 -> 5 | V26: ='LIVRE Oficial'!K25 -> 9
B27: ='LIVRE Oficial'!A25 -> 12 | C27: ='LIVRE Oficial'!B26 -> 46198 | D27: ='LIVRE Oficial'!C26 -> Daniela Mochon | E27: ='LIVRE Oficial'!D26 -> Comercial | F27: ='LIVRE Oficial'!E26 -> 0 | G27: ='LIVRE Oficial'!I26 -> Funil + Atlas | H27: ='LIVRE Oficial'!F26 -> Entregue | I27: ='LIVRE Oficial'!G26 -> 1 | J27: ='LIVRE Oficial'!H26 -> Melhoria | K27: ='LIVRE Oficial'!L26 -> LEAD | Fechar automaticamente como "lost" leads com score de 1 a 300 com motivo fechado perdido de "Score abaixo de 300" (Atlas deve apresentar a mesma mensagem no site e altas do motivo "short recusado") | L27: ='LIVRE Oficial'!V26 -> 0 | M27: ='LIVRE Oficial'!U26 -> 0 | N27: ='LIVRE Oficial'!M26 -> P | Q27: ='LIVRE Oficial'!J26 -> 0 | R27: ='LIVRE Oficial'!P26 -> 0 | S27: ='LIVRE Oficial'!Q26 -> 0 | T27: ='LIVRE Oficial'!R26 -> 0 | U27: ='LIVRE Oficial'!S26 -> 0 | V27: ='LIVRE Oficial'!K26 -> 0
B28: ='LIVRE Oficial'!A26 -> 133 | C28: ='LIVRE Oficial'!B27 -> 46183 | D28: ='LIVRE Oficial'!C27 -> Daniela Mochon | E28: ='LIVRE Oficial'!D27 -> Comercial | F28: ='LIVRE Oficial'!E27 -> 0 | G28: ='LIVRE Oficial'!I27 -> Funil + Atlas | H28: ='LIVRE Oficial'!F27 -> Backlog | I28: ='LIVRE Oficial'!G27 -> 1 | J28: ='LIVRE Oficial'!H27 -> Melhoria | K28: ='LIVRE Oficial'!L27 -> OPORTUNIDADE | Criar campo "Parceiro" (Atlas deve enviar a qual parceiro esse cliente esta vinculado) | L28: ='LIVRE Oficial'!V27 -> 0 | M28: ='LIVRE Oficial'!U27 -> Sugestão: Agrupar com a US 329942 | N28: ='LIVRE Oficial'!M27 -> 0 | Q28: ='LIVRE Oficial'!J27 -> 543212 | R28: ='LIVRE Oficial'!P27 -> 1 | S28: ='LIVRE Oficial'!Q27 -> 1 | T28: ='LIVRE Oficial'!R27 -> 1 | U28: ='LIVRE Oficial'!S27 -> 3 | V28: ='LIVRE Oficial'!K27 -> 0
B29: ='LIVRE Oficial'!A27 -> 130 | C29: ='LIVRE Oficial'!B28 -> 46238 | D29: ='LIVRE Oficial'!C28 -> Daniela Mochon | E29: ='LIVRE Oficial'!D28 -> Comercial | F29: ='LIVRE Oficial'!E28 -> 0 | G29: ='LIVRE Oficial'!I28 -> Funil | H29: ='LIVRE Oficial'!F28 -> Entregue | I29: ='LIVRE Oficial'!G28 -> 1 | J29: ='LIVRE Oficial'!H28 -> Melhoria | K29: ='LIVRE Oficial'!L28 -> OPORTUNIDADE | Substituir exibição de endereço detalhado de fornecedores por localização genérica | L29: ='LIVRE Oficial'!V28 -> 0 | M29: ='LIVRE Oficial'!U28 -> 0 | N29: ='LIVRE Oficial'!M28 -> P | Q29: ='LIVRE Oficial'!J28 -> 539556 | R29: ='LIVRE Oficial'!P28 -> 1 | S29: ='LIVRE Oficial'!Q28 -> 2 | T29: ='LIVRE Oficial'!R28 -> 2 | U29: ='LIVRE Oficial'!S28 -> 5 | V29: ='LIVRE Oficial'!K28 -> 6
B30: ='LIVRE Oficial'!A28 -> 28 | C30: ='LIVRE Oficial'!B29 -> 46238 | D30: ='LIVRE Oficial'!C29 -> Daniela Mochon | E30: ='LIVRE Oficial'!D29 -> Comercial | F30: ='LIVRE Oficial'!E29 -> 0 | G30: ='LIVRE Oficial'!I29 -> Funil | H30: ='LIVRE Oficial'!F29 -> Backlog | I30: ='LIVRE Oficial'!G29 -> 3 | J30: ='LIVRE Oficial'!H29 -> Melhoria | K30: ='LIVRE Oficial'!L29 -> OPORTUNIDADE | Preencher automaticamente a data de cobrança da primeira parcela em oportunidades de renovação | L30: ='LIVRE Oficial'!V29 -> 0 | M30: ='LIVRE Oficial'!U29 -> 0 | N30: ='LIVRE Oficial'!M29 -> M | Q30: ='LIVRE Oficial'!J29 -> 539590 | R30: ='LIVRE Oficial'!P29 -> 3 | S30: ='LIVRE Oficial'!Q29 -> 3 | T30: ='LIVRE Oficial'!R29 -> 3 | U30: ='LIVRE Oficial'!S29 -> 9 | V30: ='LIVRE Oficial'!K29 -> 0
B31: ='LIVRE Oficial'!A29 -> 26 | C31: ='LIVRE Oficial'!B30 -> 46269 | D31: ='LIVRE Oficial'!C30 -> Daniela Mochon | E31: ='LIVRE Oficial'!D30 -> Comercial | F31: ='LIVRE Oficial'!E30 -> 0 | G31: ='LIVRE Oficial'!I30 -> Funil | H31: ='LIVRE Oficial'!F30 -> Backlog | I31: ='LIVRE Oficial'!G30 -> 3 | J31: ='LIVRE Oficial'!H30 -> Melhoria | K31: ='LIVRE Oficial'!L30 -> CONTRATO | Criar categoria de contrato “Renovação – Troca de Titularidade” com regras específicas de operação e cobrança | L31: ='LIVRE Oficial'!V30 -> 0 | M31: ='LIVRE Oficial'!U30 -> 0 | N31: ='LIVRE Oficial'!M30 -> M | Q31: ='LIVRE Oficial'!J30 -> 543148 | R31: ='LIVRE Oficial'!P30 -> 3 | S31: ='LIVRE Oficial'!Q30 -> 2 | T31: ='LIVRE Oficial'!R30 -> 2 | U31: ='LIVRE Oficial'!S30 -> 7 | V31: ='LIVRE Oficial'!K30 -> 0
... B110: ='LIVRE Oficial'!A108 -> 108 | C110: ='LIVRE Oficial'!B109 -> 46154 | D110: ='LIVRE Oficial'!C109 -> Daniela Mochon | E110: ='LIVRE Oficial'!D109 -> Comercial | F110: ='LIVRE Oficial'!E109 -> 0 | G110: ='LIVRE Oficial'!I109 -> Funil | H110: ='LIVRE Oficial'!F109 -> Entregue | I110: ='LIVRE Oficial'!G109 -> 2 | J110: ='LIVRE Oficial'!H109 -> Melhoria | K110: ='LIVRE Oficial'!L109 -> CASO | Desenvolver na regra de criação de CASO de não-renovação | L110: ='LIVRE Oficial'!V109 -> 0 | M110: ='LIVRE Oficial'!U109 -> 0 | N110: ='LIVRE Oficial'!M109 -> 0 | Q110: ='LIVRE Oficial'!J109 -> 642989 | R110: ='LIVRE Oficial'!P109 -> 3 | S110: ='LIVRE Oficial'!Q109 -> 3 | T110: ='LIVRE Oficial'!R109 -> 3 | U110: ='LIVRE Oficial'!S109 -> 9 | V110: ='LIVRE Oficial'!K109 -> 2
B111: ='LIVRE Oficial'!A109 -> 109 | C111: ='LIVRE Oficial'!B110 -> 46155 | D111: ='LIVRE Oficial'!C110 -> Proativo | E111: ='LIVRE Oficial'!D110 -> Comercial | G111: ='LIVRE Oficial'!I110 -> Funil | H111: ='LIVRE Oficial'!F110 -> Entregue | I111: ='LIVRE Oficial'!G110 -> 0 | J111: ='LIVRE Oficial'!H110 -> BUG | K111: ='LIVRE Oficial'!L110 -> OPORTUNIDADE | Desenvolver correção para BUG pós Deploy em Renovação Automática | L111: ='LIVRE Oficial'!V110 -> 0 | M111: ='LIVRE Oficial'!U110 -> 0 | N111: ='LIVRE Oficial'!M110 -> P | O111: FALSE | P111: FALSE | Q111: ='LIVRE Oficial'!J110 -> 645061 | R111: ='LIVRE Oficial'!P110 -> 2 | S111: ='LIVRE Oficial'!Q110 -> 2 | T111: ='LIVRE Oficial'!R110 -> 2 | U111: ='LIVRE Oficial'!S110 -> 6
B112: ='LIVRE Oficial'!A110 -> 110 | C112: ='LIVRE Oficial'!B111 -> 46146 | D112: ='LIVRE Oficial'!C111 -> Cibele | E112: ='LIVRE Oficial'!D111 -> Comercial | G112: ='LIVRE Oficial'!I111 -> Funil | H112: ='LIVRE Oficial'!F111 -> Entregue | I112: ='LIVRE Oficial'!G111 | J112: ='LIVRE Oficial'!H111 -> Melhoria | K112: ='LIVRE Oficial'!L111 -> PERFIL | "Atendimento Livre" precisa enxergar "Nome_do_Vendedor__c" | L112: ='LIVRE Oficial'!V111 -> 0 | M112: ='LIVRE Oficial'!U111 -> 0 | N112: ='LIVRE Oficial'!M111 -> P | O112: FALSE | P112: FALSE | Q112: ='LIVRE Oficial'!J111 -> 640188 | R112: ='LIVRE Oficial'!P111 | S112: ='LIVRE Oficial'!Q111 | T112: ='LIVRE Oficial'!R111 | U112: ='LIVRE Oficial'!S111 -> #VALUE! | V112: ='LIVRE Oficial'!K111 -> 16
B113: ='LIVRE Oficial'!A111 -> 107 | C113: ='LIVRE Oficial'!B112 -> 46162 | D113: ='LIVRE Oficial'!C112 -> Daniela Mochon | E113: ='LIVRE Oficial'!D112 -> Comercial | G113: ='LIVRE Oficial'!I112 -> Funil | H113: ='LIVRE Oficial'!F112 -> Entregue | I113: ='LIVRE Oficial'!G112 -> 0 | J113: ='LIVRE Oficial'!H112 -> Melhoria | K113: ='LIVRE Oficial'!L112 -> OPORTUNIDADE | Complemento de Distribuição de Leads – Inserir ID e NOME do Gestor da Oportunidade | L113: ='LIVRE Oficial'!V112 -> 0 | M113: ='LIVRE Oficial'!U112 -> 0 | N113: ='LIVRE Oficial'!M112 -> 0 | O113: FALSE | P113: FALSE | Q113: ='LIVRE Oficial'!J112 -> 656857 | R113: ='LIVRE Oficial'!P112 -> 1 | S113: ='LIVRE Oficial'!Q112 -> 2 | T113: ='LIVRE Oficial'!R112 -> 1 | U113: ='LIVRE Oficial'!S112 -> 4 | V113: ='LIVRE Oficial'!K112 -> -
B114: ='LIVRE Oficial'!A112 -> 112 | C114: ='LIVRE Oficial'!B113 -> 46163 | D114: ='LIVRE Oficial'!C113 -> Proativo | E114: ='LIVRE Oficial'!D113 -> Funil | G114: ='LIVRE Oficial'!I113 -> Funil | H114: ='LIVRE Oficial'!F113 -> Entregue | I114: ='LIVRE Oficial'!G113 -> 0 | J114: ='LIVRE Oficial'!H113 -> BUG | K114: ='LIVRE Oficial'!L113 -> OPORTUNIDADE | Desenvolver correção do disparo da Distribuição de Lead | L114: ='LIVRE Oficial'!V113 -> 0 | M114: ='LIVRE Oficial'!U113 -> 0 | N114: ='LIVRE Oficial'!M113 -> P | O114: FALSE | P114: FALSE | Q114: ='LIVRE Oficial'!J113 -> 657117 | R114: ='LIVRE Oficial'!P113 -> 1 | S114: ='LIVRE Oficial'!Q113 -> 1 | T114: ='LIVRE Oficial'!R113 -> 1 | U114: ='LIVRE Oficial'!S113 -> 3 | V114: ='LIVRE Oficial'!K113 -> 1
B115: ='LIVRE Oficial'!A113 -> 113 | C115: ='LIVRE Oficial'!B114 -> 46163 | D115: ='LIVRE Oficial'!C114 -> Daniela Mochon | E115: ='LIVRE Oficial'!D114 -> Comercial | G115: ='LIVRE Oficial'!I114 -> Funil | H115: ='LIVRE Oficial'!F114 -> Entregue | I115: ='LIVRE Oficial'!G114 -> 0 | J115: ='LIVRE Oficial'!H114 -> Melhoria | K115: ='LIVRE Oficial'!L114 -> LEAD | Desenvolver Opção de "Renovação" na picklist do LeadSource | L115: ='LIVRE Oficial'!V114 -> 0 | M115: ='LIVRE Oficial'!U114 -> Fora do Escopo SPRINT 04 | N115: ='LIVRE Oficial'!M114 -> P | O115: FALSE | P115: FALSE | Q115: ='LIVRE Oficial'!J114 -> 657177 | R115: ='LIVRE Oficial'!P114 -> 1 | S115: ='LIVRE Oficial'!Q114 -> 1 | T115: ='LIVRE Oficial'!R114 -> 1 | U115: ='LIVRE Oficial'!S114 -> 3 | V115: ='LIVRE Oficial'!K114 -> 1
B116: ='LIVRE Oficial'!A114 -> 114 | C116: ='LIVRE Oficial'!B115 -> 46164 | D116: ='LIVRE Oficial'!C115 -> Daniela Mochon | E116: ='LIVRE Oficial'!D115 -> Comercial | G116: ='LIVRE Oficial'!I115 -> Funil | H116: ='LIVRE Oficial'!F115 -> Entregue | I116: ='LIVRE Oficial'!G115 -> 0 | J116: ='LIVRE Oficial'!H115 -> Melhoria | K116: ='LIVRE Oficial'!L115 -> OPORTUNIDADE | Desenvolver cópia do nome do Owner para o Campo "Nome do Vendedor" | L116: ='LIVRE Oficial'!V115 -> 0 | M116: ='LIVRE Oficial'!U115 -> 0 | N116: ='LIVRE Oficial'!M115 -> P | O116: FALSE | P116: FALSE | Q116: ='LIVRE Oficial'!J115 -> 657521 | R116: ='LIVRE Oficial'!P115 -> 1 | S116: ='LIVRE Oficial'!Q115 -> 1 | T116: ='LIVRE Oficial'!R115 -> 1 | U116: ='LIVRE Oficial'!S115 -> 3 | V116: ='LIVRE Oficial'!K115 -> 1
B117: ='LIVRE Oficial'!A115 -> 115 | C117: ='LIVRE Oficial'!B116 -> 46167 | D117: ='LIVRE Oficial'!C116 -> Daniela Mochon | E117: ='LIVRE Oficial'!D116 -> Comercial | G117: ='LIVRE Oficial'!I116 -> Funil | H117: ='LIVRE Oficial'!F116 -> Entregue | I117: ='LIVRE Oficial'!G116 -> 0 | J117: ='LIVRE Oficial'!H116 -> BUG | K117: ='LIVRE Oficial'!L116 -> LEAD | Desenvolver correção para LeadSource Nulo | L117: ='LIVRE Oficial'!V116 -> 0 | M117: ='LIVRE Oficial'!U116 -> Fora do Escopo SPRINT 04 | N117: ='LIVRE Oficial'!M116 -> P | O117: FALSE | P117: FALSE | Q117: ='LIVRE Oficial'!J116 -> 658406 | R117: ='LIVRE Oficial'!P116 -> 1 | S117: ='LIVRE Oficial'!Q116 -> 1 | T117: ='LIVRE Oficial'!R116 -> 1 | U117: ='LIVRE Oficial'!S116 -> 3 | V117: ='LIVRE Oficial'!K116 -> 1
B118: ='LIVRE Oficial'!A116 -> 116 | C118: ='LIVRE Oficial'!B117 -> 46170 | D118: ='LIVRE Oficial'!C117 -> Daniela Mochon | E118: ='LIVRE Oficial'!D117 -> Comercial | G118: ='LIVRE Oficial'!I117 -> Funil | H118: ='LIVRE Oficial'!F117 -> Entregue | I118: ='LIVRE Oficial'!G117 -> 0 | J118: ='LIVRE Oficial'!H117 -> Melhoria | K118: ='LIVRE Oficial'!L117 -> OPORTUNIDADE | Desenvolver novo balanceamento de Distribuição de Leads | L118: ='LIVRE Oficial'!V117 -> 0 | M118: ='LIVRE Oficial'!U117 -> Fora do Escopo SPRINT 04 | N118: ='LIVRE Oficial'!M117 -> 0 | O118: FALSE | P118: FALSE | Q118: ='LIVRE Oficial'!J117 -> 659617 | R118: ='LIVRE Oficial'!P117 -> 1 | S118: ='LIVRE Oficial'!Q117 -> 1 | T118: ='LIVRE Oficial'!R117 -> 1 | U118: ='LIVRE Oficial'!S117 -> 3 | V118: ='LIVRE Oficial'!K117 -> 1
B119: ='LIVRE Oficial'!A117 -> 117 | C119: ='LIVRE Oficial'!B118 -> 46170 | D119: ='LIVRE Oficial'!C118 -> Proativo | E119: ='LIVRE Oficial'!D118 -> Funil | G119: ='LIVRE Oficial'!I118 -> Funil | H119: ='LIVRE Oficial'!F118 -> Entregue | I119: ='LIVRE Oficial'!G118 -> 0 | J119: ='LIVRE Oficial'!H118 -> BUG | K119: ='LIVRE Oficial'!L118 -> OPORTUNIDADE | Desenvolver Status da Análise de Crédito em Branco em Cenários de Renovação | L119: ='LIVRE Oficial'!V118 -> 0 | M119: ='LIVRE Oficial'!U118 -> 0 | N119: ='LIVRE Oficial'!M118 -> P | O119: FALSE | P119: FALSE | Q119: ='LIVRE Oficial'!J118 -> 659679 | R119: ='LIVRE Oficial'!P118 -> 1 | S119: ='LIVRE Oficial'!Q118 -> 1 | T119: ='LIVRE Oficial'!R118 -> 1 | U119: ='LIVRE Oficial'!S118 -> 3 | V119: ='LIVRE Oficial'!K118 -> 2
B120: ='LIVRE Oficial'!A118 -> 118 | C120: ='LIVRE Oficial'!B119 -> 46223 | D120: ='LIVRE Oficial'!C119 -> Jéssica Fachina | E120: ='LIVRE Oficial'!D119 -> Comercial | G120: ='LIVRE Oficial'!I119 -> Funil | H120: ='LIVRE Oficial'!F119 -> Priorizado Proxima Sprint | I120: ='LIVRE Oficial'!G119 -> 0 | J120: ='LIVRE Oficial'!H119 -> Melhoria | K120: ='LIVRE Oficial'!L119 -> OPORTUNIDADE | Nova alteração na Regra de Distribuição de Lead - Zeus 600-1000 e Nexi 0-599 | L120: ='LIVRE Oficial'!V119 -> 0 | M120: ='LIVRE Oficial'!U119 -> 0 | N120: ='LIVRE Oficial'!M119 -> 0 | O120: FALSE | P120: FALSE | Q120: ='LIVRE Oficial'!J119 -> 713714 | R120: ='LIVRE Oficial'!P119 -> 0 | S120: ='LIVRE Oficial'!Q119 -> 0 | T120: ='LIVRE Oficial'!R119 -> 0 | U120: ='LIVRE Oficial'!S119 -> 0 | V120: ='LIVRE Oficial'!K119 -> 1
B121: ='LIVRE Oficial'!A119 -> 138 | C121: ='LIVRE Oficial'!B120 -> 46174 | D121: ='LIVRE Oficial'!C120 -> Daniela Mochon | E121: ='LIVRE Oficial'!D120 -> Comercial | G121: ='LIVRE Oficial'!I120 -> Funil | H121: ='LIVRE Oficial'!F120 -> Entregue | I121: ='LIVRE Oficial'!G120 -> 0 | J121: ='LIVRE Oficial'!H120 -> Melhoria | K121: ='LIVRE Oficial'!L120 -> OPORTUNIDADE | Desenvolver Batch para aumentar frequência de geração de Pedido de Compra | L121: ='LIVRE Oficial'!V120 -> 0 | M121: ='LIVRE Oficial'!U120 -> 0 | N121: ='LIVRE Oficial'!M120 -> P | O121: FALSE | P121: FALSE | Q121: ='LIVRE Oficial'!J120 -> 660361 | R121: ='LIVRE Oficial'!P120 -> 0 | S121: ='LIVRE Oficial'!Q120 -> 0 | T121: ='LIVRE Oficial'!R120 -> 0 | U121: ='LIVRE Oficial'!S120 -> 0 | V121: ='LIVRE Oficial'!K120 -> 2
B122: ='LIVRE Oficial'!A120 -> 120 | C122: ='LIVRE Oficial'!B121 -> 45845 | D122: ='LIVRE Oficial'!C121 -> Daniela Mochon | E122: ='LIVRE Oficial'!D121 -> Comercial | G122: ='LIVRE Oficial'!I121 -> Funil | H122: ='LIVRE Oficial'!F121 -> Removido | I122: ='LIVRE Oficial'!G121 -> 1 | J122: ='LIVRE Oficial'!H121 -> Melhoria | K122: ='LIVRE Oficial'!L121 -> CASO | Liberação de acesso ao campo CNPJ_Fornecedor_Relacionado__c para perfil Front Office Comercial Leves | L122: ='LIVRE Oficial'!V121 -> 0 | M122: ='LIVRE Oficial'!U121 -> 0 | N122: ='LIVRE Oficial'!M121 -> P | O122: FALSE | P122: FALSE | Q122: ='LIVRE Oficial'!J121 -> 312689 | R122: ='LIVRE Oficial'!P121 -> 1 | S122: ='LIVRE Oficial'!Q121 -> 3 | T122: ='LIVRE Oficial'!R121 -> 3 | U122: ='LIVRE Oficial'!S121 -> 7 | V122: ='LIVRE Oficial'!K121 -> 0
B123: ='LIVRE Oficial'!A121 -> 30 | C123: ='LIVRE Oficial'!B122 -> 46269 | D123: ='LIVRE Oficial'!C122 -> Daniela Mochon | E123: ='LIVRE Oficial'!D122 -> Comercial | G123: ='LIVRE Oficial'!I122 -> Funil | H123: ='LIVRE Oficial'!F122 -> Entregue | I123: ='LIVRE Oficial'!G122 -> 1 | J123: ='LIVRE Oficial'!H122 -> Melhoria | K123: ='LIVRE Oficial'!L122 -> OPORTUNIDADE | Disparar e-mail ao vendedor quando o crédito reprovar uma renovação | L123: ='LIVRE Oficial'!V122 -> 0 | M123: ='LIVRE Oficial'!U122 -> 0 | N123: ='LIVRE Oficial'!M122 -> M | O123: FALSE | P123: FALSE | Q123: ='LIVRE Oficial'!J122 -> 543213 | R123: ='LIVRE Oficial'!P122 -> 1 | S123: ='LIVRE Oficial'!Q122 -> 1 | T123: ='LIVRE Oficial'!R122 -> 1 | U123: ='LIVRE Oficial'!S122 -> 3 | V123: ='LIVRE Oficial'!K122 -> 11
... B130: ='LIVRE Oficial'!A128 -> 16 | C130: ='LIVRE Oficial'!B129 -> 46191 | D130: ='LIVRE Oficial'!C129 -> Daniela Mochon | E130: ='LIVRE Oficial'!D129 -> Comercial | G130: ='LIVRE Oficial'!I129 -> Funil | H130: ='LIVRE Oficial'!F129 -> Entregue | I130: ='LIVRE Oficial'!G129 -> 1 | J130: ='LIVRE Oficial'!H129 -> Melhoria | K130: ='LIVRE Oficial'!L129 -> CASO | Ajuste da regra de criação de caso para desmobilização, contabilizando dias úteis e removendo a regra de fechamento automatico da oportunidade | L130: ='LIVRE Oficial'!V129 -> 0 | M130: ='LIVRE Oficial'!U129 -> 0 | N130: ='LIVRE Oficial'!M129 -> P | O130: FALSE | P130: FALSE | Q130: ='LIVRE Oficial'!J129 -> 679032 | R130: ='LIVRE Oficial'!P129 -> 0 | S130: ='LIVRE Oficial'!Q129 -> 0 | T130: ='LIVRE Oficial'!R129 -> 0 | U130: ='LIVRE Oficial'!S129 -> 0 | V130: ='LIVRE Oficial'!K129 -> 1

Sheet Planilha2
A1: Resumo Melhoria | B1: Descrição | C1: Valoração | D1: Prioridade | E1: Produto
A2: Ajuste plano de manutenção TA, Data emissão de TA | B2: Verificar Ene sobre plano de manutenção e se mantemos esses dois ponto na mesma melhoria | C2: G | D2: 1 | E2: Fleet
A3: PROJETO Crédito - Integração Documentação | B3: Interação efetiva do cliente no envio de documentos| cliente enviar a documentação quando entrasse no crédito | C3: ? | D3: 2 | E3: Fleet
A4: PROJETO Crédito - OCR & IA para balanços e demais doc do cliente | fornecedor que todas vez que o cliente mandar a documentação da empresa a IA ler e ver se esta correto | B4: Acelerar o time-to-yes focando em dados e não preenchimentos operacionais| | C4: ? | D4: 3 | E4: Fleet
A5: Alterar vinculo do contrato no meio da oportunidade e não apenas no inicio | B5: criar oportunidade só consigo vincular quando crio a op, e não deixa alterar, com isso precisa fazer do começo novamente a oportunidade | opção de vinular ou criar um novo, precisamos conseguir retirar o vinculo ou criar o vinculo no meio do fluxo | C5: ? | D5: 4 | E5: Fleet
A6: ajuste CNPJ Alfanumerico, | B6: envolve reforma tributaria | C6: ? | D6: 5 | E6: Fleet
A7: Anexar a Documentação todas as vezes - não replica para todas as oportunidades do mesmo cliente, ver a possibilidade de os documentos ficarem vinculados a conta e o sistema ter a opção de pegar da conta sem a necessidade de incluir um a um a cada proposta fechada | B7: aprodundas com crédito e adm | C7: ? | D7: 6 | E7: Fleet
A8: Identificação de novos campos para integração ao contrato do locavia Exemplo:tipo de rodagem, tipo de indice de reajuste se for media e menor | B8: Necessário adicionar o campo Tipo de rodagem (IRIS_Tipo_de_rodagem__c) que está dentro do objeto linhas da cotação para a integração junto ao Locavia | esse é um dos campos mas precisamos ver com a Mary não tem outros campos na mesma situação | C8: ? | D8: 7 | E8: Fleet
A9: Integração Whatsapp - Sales Force | B9: Integrar whatsapp ao Sales Force com leitura de informações passadas pelo cliente como Nome, CNPJ e numero de celular para que o lead seja criado de maneira automatizado e de forma que o CNPJ seja validado nas integrações externas de classificação de cliente e de dados da receita federal.| pessoal do seminovos ja faz dessa forma | precisamos refinar pra enteder com time de negocio | C9: ? | D9: 8 | E9: Fleet
A10: Identificação dos aprovadores de cotação relatorio e tela | B10: |18/02/2026 09:35 Pedro Henrique Franco: Descrição - Conforme falado em chatter, estamos com itens impactando diretamente a diretoria e performance do time, portanto solicito melhoria do tema. Resumo: Identificação de aprovadores da oportunidade/cotação, bem como adição de novas informações nas aprovações da op. Os detalhes estão no Word anexado no chamado. Obrigado | C10: M | D10: 9 | E10: Fleet
A11: Identificação dos aprovadores de oportunidade e matriz juridica, relatorio e tela | B11: |18/02/2026 09:35 Pedro Henrique Franco: Descrição - Conforme falado em chatter, estamos com itens impactando diretamente a diretoria e performance do time, portanto solicito melhoria do tema. Resumo: Identificação de aprovadores da oportunidade/cotação, bem como adição de novas informações nas aprovações da op. Os detalhes estão no Word anexado no chamado. Obrigado | C11: M | D11: 10 | E11: Fleet
A12: PROJETO Harmonização CRM (Fleet & Livre) | B12: Evitar desenvolvimentos duplicados face itens ocorridos no Fleet durante o IRIS|COMPLEXO, esteiras de fleet e livre deixar mais proximo possivel | C12: ? | D12: 11 | E12: Fleet
A13: PROJETO Score do Cliente - Novo Cliente | B13: Evitar tempo do Comercial em clientes fora de perfil levando em consideração itens adicionais ao pré-rating| ter um Score interno de cliente, a gente ter uma avaliação e algo da unidas (clientes novos) | C13: ? | D13: 12 | E13: Fleet
A14: GAP KILLING - Envio Antecipado de Contrato para o cliente e Análise Jurídica | B14: botão de analise antecipada dentro do SF, elaw esta preparada para isso apenas o contrato , não envia TA- PODE CRIAR EM QUALQUER momento até a elaboração da minuta | C14: G | E14: Fleet
A15: GAP KILLING - Cotação de leaseback | B15: Complexo, produto que não temos hoje, deve ser trata no futuro vendo grande impacto | C15: G | E15: Fleet
A16: Oportunidade Futura Pós Lost | B16: quando da perda manual, ter a opção de criar uma oportunidade futura. | C16: GG | E16: Fleet
A17: PROJETO SLA (Fases/Subfases da Oportunidade) | B17: |18/02/2026 09:35 Pedro Henrique Franco: Descrição - Conforme falado em chatter, estamos com itens impactando diretamente a diretoria e performance do time, portanto solicito melhoria do tema. Resumo: Identificação de SLA das fases/subfases Os detalhes estão no Word anexado no chamado. Obrigado | C17: M | E17: Fleet
A18: Leads Duplicados *Prioritario* | B18: Leads que chegam repetidos, devem ser agregados ao lead original se estiver em aberto, permitindo que o atendente que esta trabalhando no lead original, tenha acesso aos dados do lead novo, ao mesmo tempo que o lead novo não seja trabalhado por outro atendente ou em momento separado (Verificar se melhoria esta sendo trabalhada na Squad do Rac Corporativo)|07/02/2026 19:03 Abgail Gomes da Silva Tantsch: Descrição - Tratamento de Leads Duplicados no status NOVO Pessoal, tudo bem? Temos enfrentado um problema recorrente com entrada de Leads duplicados, principalmente quando: já existe um Lead em ATENDIMENTO e novos Leads entram com as mesmas informações (telefone, e‑mail ou empresa) ficando todos no status NOVO, espalhados entre diferentes donos Isso gera: retrabalho risco de contato duplicado com o cliente dificuldade de identificar qual Lead está sendo efetivamente atendido Solicitação: Gostaríamos de avaliar uma configuração onde: Todo Lead novo, ao entrar no Salesforce, verifique se já existe um Lead com as mesmas informações em status ATENDIMENTO Caso exista, o novo Lead: não fique solto como “NOVO” seja agrupado / relacionado ao Lead já existente ou tenha seu status ajustado automaticamente O objetivo é manter todos os registros do mesmo contato concentrados, facilitando o acompanhamento e evitando retrabalho no time. Essa melhoria ajudaria muito a produtividade e a qualidade do atendimento. Obrigada! | C18: M | E18: Fleet
A19: Formato +55 | B19: Incluir o formato +55 automaticamente para os telefones que não possuem essa dado ao integrar o lead no sales force (verificar possibilidade de usar essa melhoria tb para os leads Livre PF)|10/03/2026 16:35 Alexandre Alberto Dea dos Santos: Descrição - Formato +55 - Incluir o formato +55 automaticamente para os telefones que não possuem essa dado ao integrar o lead no sales force (verificar possibilidade de usar essa melhoria tb para os leads Livre PF) | Aline 14.04 : é apenas o formato da ingração quando o lead entrar no sistema independente da origem, verificar sobre o ajuste na Api que vem do autocerto ja com o ajuste, desenvolvimento pelo Heitor | C19: M | E19: Fleet
A20: Oportunidades não geradas | B20: Atualmente quando existe uma conversão de lead com duas áreas de interesse diferentes, porém em uma dela por algum motivo a conversão da erro, o sistema gera a oportunidade pra uma das diretorias e não gera para a que deu erro. O problema é que não existe mensagem informando do erro ou da falta de informação para gerar a outra oportunidade. Caso aconteceu 2 vezes em que o DDD do cliente com interesse em pesados e PME era divergente do endereço da empresa. Ao converter esse lead gerou apenas oportunidade de PME e não gerou nem avisou que não gerou a oportunidade de Pesados. Avaliar possibilidade de lista de distribuição ser por cidade e não DDD, evitando o erro de UF diferente de DDD (Planejamento Comercial)|11/03/2026 17:15 Alexandre Alberto Dea dos Santos: Descrição - Oportunidades não geradas - Atualmente quando existe uma conversão de lead com duas áreas de interesse diferentes, porém em uma dela por algum motivo a conversão da erro, o sistema gera a oportunidade pra uma das diretorias e não gera para a que deu erro. O problema é que não existe mensagem informando do erro ou da falta de informação para gerar a outra oportunidade. Caso aconteceu 2 vezes em que o DDD do cliente com interesse em pesados e PME era divergente do endereço da empresa. Ao converter esse lead gerou apenas oportunidade de PME e não gerou nem avisou que não gerou a oportunidade de Pesados. Para que o problema não volte a ocorrer, além de msg de alerta de erro, avaliar possibilidade de lista de distribuição ser por cidade e não DDD, evitando o erro de UF diferente de DDD informado pela integração da receita federal (Envolver Planejamento Comercial na resolução dessa melhoria) | C20: M | E20: Fleet
A21: Redistribuição de Leads | B21: Atualmente é possível enviar um lead ou vários leads para uma pessoa por vez. Precisamos que seja possível enviar vários leads para mais de uma pessoa por vez e que se houver mais de uma pessoa para recebe-lo que seja dividido igualmente o volume de leads encaminhados entre as pessoas que vão recebe-los|11/03/2026 17:21 Alexandre Alberto Dea dos Santos: Descrição - Redistribuição de Leads - Atualmente é possível enviar um lead ou vários leads para uma pessoa por vez. Precisamos que seja possível enviar vários leads para mais de uma pessoa por vez e que se houver mais de uma pessoa para recebe-lo que seja dividido igualmente o volume de leads encaminhados entre as pessoas que vão recebe-los | C21: M | E21: Fleet
A22: GAP KILLING - Cotação de serviços para terceiros | B22: Criação de proposta e cotação para serviço terceiro| | C22: ? | E22: Fleet
A23: Transferência Automática Hunter para Farmer | B23: precisamos desenhar todo os fluxo e entendimento | C23: ? | E23: Fleet
A24: Transferência Automática de Farmer para Hunter (ex clientes) | B24: precisamos desenhar todo os fluxo e entendimento | C24: ? | E24: Fleet
A25: trazer quantidade de pneu automaticamente do locavia | B25: Complexo- precisava trazer do cadastro do produto, exemplo gol 4 pensar algo mais automatico, com prazo e km, e entender com pricing se é possivel | C25: ? | E25: Fleet
... A33: PROJETO Simplificação & Reavaliação (SAP Comissions) | B33: Redesenho para simplificar a dependência do SAP devido altos custos em simples alterações| | C33: ? | E33: Fleet

Sheet LIVRE Oficial
A1: ID | B1: Data da Inserção | C1: Solicitante | D1: Área | E1: Chamado | F1: Status | G1: Avaliação área de Negocio | H1: Classificação | I1: Squad | J1: Nº Azure | K1: Prioridade | L1: Resumo Melhoria | M1: Tamanho | N1: Comitê de TI | O1: Squad On Going | P1: Gravidade | Q1: Urgência | R1: Tendência | S1: Resultado GUT | T1: Historia | U1: OBS | V1: Descrição
A2: 1 | B2: 45758 | C2: Daniela Mochon | D2: Comercial | F2: Entregue | G2: 3 | H2: Melhoria | I2: Funil | J2: 364684 | K2: 1 | L2: LEAD | Distribuição Automática e Inteligente de Leads no Salesforce (Vendedores Internos) | M2: G | N2: FALSE | O2: FALSE | P2: 1 | Q2: 2 | R2: 3 | S2: =P2+Q2+R2 -> 6
A3: 131 | B3: 46171 | C3: Daniela Mochon | D3: Comercial | F3: Aguardando Refinamento de Negócio | G3: 1 | H3: Melhoria | I3: Funil | J3: 679614 | K3: 4 | L3: LEAD | Criação do campo “LeadPrincipalCPF” | M3: P | O3: TRUE
A4: 27 | B4: 46238 | C4: Daniela Mochon | D4: Comercial | F4: Backlog | G4: 3 | H4: Melhoria | I4: Funil | J4: 539582 | L4: CONTRATO | Atualizar automaticamente status e dados de contratos e pedidos via integração entre Salesforce e Locavia | M4: GG | N4: TRUE | P4: 3 | Q4: 2 | R4: 3 | S4: =P4+Q4+R4 -> 8
A5: 4 | B5: 45754 | C5: Daniela Mochon | D5: Comercial | F5: Entregue | H5: Melhoria | I5: Funil | J5: 312387 | L5: ATLAS | Remover a limitação de 150 propostas na exibição com filtros de Status aplicados em "Minhas propostas" | S5: =P5+Q5+R5 -> #VALUE!
A6: 5 | B6: 9609 | C6: Daniela Mochon | D6: Comercial | E6: C2604-24461 | F6: Entregue | G6: 1 | H6: BUG | I6: Funil | J6: 593226 | K6: 9 | L6: CONTA | Permitir alteração manual do nome da Conta para registros criados de forma sistêmica | P6: 1 | Q6: 3 | R6: 3 | S6: =P6+Q6+R6 -> 7
A7: 6 | B7: 9454 | C7: Daniela Mochon | D7: Comercial | F7: Entregue | G7: 3 | H7: Melhoria | I7: Funil | J7: 371328 | K7: 4 | L7: OPORTUNIDADE | Criação de Nova Oportunidade a partir de Fechamento da Op de Renovação | P7: 3 | Q7: 3 | R7: 3 | S7: =P7+Q7+R7 -> 9
A8: 7 | B8: 9616 | C8: Pedro Henrique | D8: Comercial | E8: C2604-17343 | F8: Entregue | G8: 1 | H8: BUG | I8: Funil | J8: 625264 | K8: 13 | L8: OPORTUNIDADE | Desenvolver Correção do Status da Análise de Crédito | P8: 2 | Q8: 1 | R8: 2 | S8: =P8+Q8+R8 -> 5
A9: 8 | B9: 9614 | C9: Monique Evelin | D9: Crédito | F9: Entregue | G9: 1 | H9: Melhoria | I9: Funil | J9: 625328 | K9: 22 | L9: CONTA | Botão Manual para Consulta SERASA na Conta (Pessoa Física) | M9: M | P9: 1 | Q9: 1 | R9: 1 | S9: =P9+Q9+R9 -> 3
A10: 9 | B10: 9551 | C10: Daniela Mochon | D10: Comercial | F10: Entregue | G10: 1 | H10: Melhoria | I10: Funil | J10: 397306 | K10: 2 | L10: QUOTE | Desenvolver envio de Opcionais no Pedido de Compra para o Locavia | M10: M | O10: TRUE | P10: 2 | Q10: 2 | R10: 1 | S10: =P10+Q10+R10 -> 5
A11: 10 | B11: 46269 | C11: Daniela Mochon | D11: Comercial | F11: Entregue | G11: 1 | H11: BUG | I11: Funil | J11: 543229 | K11: 21 | L11: OPORTUNIDADE | Desenvolver correção para atualização do motivo do pedido de compra em cenários de renovação | M11: P | P11: 1 | Q11: 1 | R11: 1 | S11: =P11+Q11+R11 -> 3
A12: 11 | B12: 46269 | C12: Daniela Mochon | D12: Comercial | F12: Entregue | G12: 1 | H12: Melhoria | I12: Funil | J12: 543196 | K12: 14 | L12: OPORTUNIDADE | Permitir geração de pedido de compra sem delay de 8 dias para casos de retenção de clientes | M12: M | P12: 2 | Q12: 2 | R12: 1 | S12: =P12+Q12+R12 -> 5
A13: 119 | B13: 46170 | C13: Daniela Mochon | D13: Comercial | F13: Entregue | H13: Melhoria | I13: Funil | J13: 660405 | K13: 1 | L13: CONTRATO | Criar campos de controle para integração de retorno de assinatura contrato (Authentique) | M13: G | N13: FALSE | O13: TRUE | P13: 1 | Q13: 1 | R13: 1 | S13: =P13+Q13+R13 -> 3 | U13: Fora do Escopo SPRINT 04
A14: 13 | B14: 9611 | C14: Proativo | D14: Funil | F14: Entregue | H14: BUG | I14: Funil | J14: 594558 | L14: ASSET - Stauts do Ativo Fleet aparecendo no Livre | S14: =P14+Q14+R14 -> #VALUE!
A15: 140 | B15: 46223 | C15: Jéssica Fachina | D15: Funil Crédito | F15: Entregue | H15: Melhoria | I15: Funil | J15: 706718 | L15: OPORTUNIDADE | Enviar novas informações da proposta de Renovação para a Plataforma de Crédito | M15: M | O15: TRUE
A16: 141 | B16: 46224 | C16: Jéssica Fachina | D16: Funil + Atlas | F16: Entregue | H16: Melhoria | I16: Funil + Atlas | J16: 706680 | K16: 1 | L16: OPORTUNIDADE | Desenvolver novas regras de Desatrelamento V2 | M16: M | O16: TRUE
A17: 144 | B17: 46230 | C17: Jéssica Fachina | D17: Funil | F17: Cancelado | H17: Melhoria | I17: Site | K17: 1 | L17: Alterar a ordem do fluxo para Assinatura e depois Pagamento
A18: 121 | B18: 46174 | C18: Daniela Mochon | D18: Comercial | F18: Entregue | H18: Melhoria | I18: Funil | J18: 661063 | K18: 2 | L18: OPORTUNIDADE | Desatrelamento Automático de Vendedor | M18: M | O18: TRUE | S18: =P18+Q18+R18 -> 0
A19: 122 | B19: 46174 | C19: Daniela Mochon | D19: Comercial | F19: Entregue | H19: BUG | I19: Funil | J19: - | K19: 2 | L19: BUG | Nas trocas ou alterações de vendedor, apenas o ID é atualizado e as outras informações ficam incorretas | M19: P | O19: TRUE | S19: =P19+Q19+R19 -> 0 | U19: Sprint 8
B20: 46197 | C20: Daniela Mochon | D20: Comercial | F20: Entregue | G20: 1 | H20: Melhoria | I20: Funil & Atlas | J20: 679043 | L20: OPORTUNIDADE | Adicionar campo de "Prazo de Entrega Informado ao cliente" | M20: P | O20: TRUE
A21: 25 | B21: 46238 | C21: Daniela Mochon | D21: Comercial | F21: Entregue | G21: 3 | H21: Melhoria | I21: Funil | J21: 539594 | K21: 5 | L21: OPORTUNIDADE | Garantir o envio e registro do desconto de 3% do Atlas para o Salesforce | P21: 3 | Q21: 2 | R21: 3 | S21: =P21+Q21+R21 -> 8 | U21: Entregue a parte funcional e API do lado do SF. Aguardando Atlas
A22: 135 | B22: 46210 | C22: Jéssica Fachina | D22: Comercial | F22: Entregue | H22: Melhoria | I22: Funil + Atlas | J22: 706752 | L22: LEAD | Encaminhar automaticamente para LOST Leads com Score inferior a 300 | M22: M
A23: 129 | B23: 46182 | C23: Daniela Mochon | D23: Comercial | F23: Entregue | H23: Melhoria | I23: Funil | J23: 670511 | K23: 3 | L23: Enviar notificação ao vendedor quando um novo lead for distribuido a ele | M23: P | O23: TRUE
A24: 31 | B24: 9427 | C24: Daniela Mochon | D24: Comercial | F24: Backlog | H24: Melhoria | I24: Funil | J24: 358303 | L24: LEAD | Serviço de Consulta de CEP do Funil de Vendas | M24: M | N24: TRUE | S24: =P24+Q24+R24 -> #VALUE!
A25: 12 | B25: 9616 | C25: Daniela Mochon | D25: Comercial | F25: Entregue | G25: 1 | H25: Melhoria | I25: Funil | J25: 625264 | K25: 9 | L25: OPORTUNIDADE | Desenvolver Correção do Status da Análise de Crédito | P25: 2 | Q25: 1 | R25: 2 | S25: =P25+Q25+R25 -> 5
A26: 133 | B26: 46198 | C26: Daniela Mochon | D26: Comercial | F26: Entregue | G26: 1 | H26: Melhoria | I26: Funil + Atlas | L26: LEAD | Fechar automaticamente como "lost" leads com score de 1 a 300 com motivo fechado perdido de "Score abaixo de 300" (Atlas deve apresentar a mesma mensagem no site e altas do motivo "short recusado") | M26: P | O26: TRUE
A27: 130 | B27: 46183 | C27: Daniela Mochon | D27: Comercial | F27: Backlog | G27: 1 | H27: Melhoria | I27: Funil + Atlas | J27: 543212 | L27: OPORTUNIDADE | Criar campo "Parceiro" (Atlas deve enviar a qual parceiro esse cliente esta vinculado) | O27: TRUE | P27: 1 | Q27: 1 | R27: 1 | S27: =P27+Q27+R27 -> 3 | U27: Sugestão: Agrupar com a US 329942
A28: 28 | B28: 46238 | C28: Daniela Mochon | D28: Comercial | F28: Entregue | G28: 1 | H28: Melhoria | I28: Funil | J28: 539556 | K28: 6 | L28: OPORTUNIDADE | Substituir exibição de endereço detalhado de fornecedores por localização genérica | M28: P | O28: TRUE | P28: 1 | Q28: 2 | R28: 2 | S28: =P28+Q28+R28 -> 5
A29: 26 | B29: 46238 | C29: Daniela Mochon | D29: Comercial | F29: Backlog | G29: 3 | H29: Melhoria | I29: Funil | J29: 539590 | L29: OPORTUNIDADE | Preencher automaticamente a data de cobrança da primeira parcela em oportunidades de renovação | M29: M | N29: TRUE | O29: FALSE | P29: 3 | Q29: 3 | R29: 3 | S29: =P29+Q29+R29 -> 9
A30: 22 | B30: 46269 | C30: Daniela Mochon | D30: Comercial | F30: Backlog | G30: 3 | H30: Melhoria | I30: Funil | J30: 543148 | L30: CONTRATO | Criar categoria de contrato “Renovação – Troca de Titularidade” com regras específicas de operação e cobrança | M30: M | N30: TRUE | P30: 3 | Q30: 2 | R30: 2 | S30: =P30+Q30+R30 -> 7
A31: 23 | B31: 46238 | C31: Daniela Mochon | D31: Comercial | F31: Backlog | G31: 1 | H31: Melhoria | I31: Funil | J31: 539664 | L31: OPORTUNIDADE | Criar e preencher o campo “Revendedor Dono da Conta” para controle de comissionamentos | M31: P | O31: TRUE | P31: 1 | Q31: 3 | R31: 3 | S31: =P31+Q31+R31 -> 7
A32: 32 | B32: 9518 | C32: Daniela Mochon | D32: Comercial | E32: C2601-22639 | F32: Entregue | G32: 2 | H32: BUG | I32: Funil | J32: 389294 | K32: 2 | L32: CONTRATO | Tornar FirstName não obrigatório na criação de Contrato | P32: 3 | Q32: 3 | R32: 3 | S32: =P32+Q32+R32 -> 9
A33: 33 | B33: 9579 | C33: Proativo | D33: Funil | F33: Entregue | G33: 1 | H33: BUG | I33: Funil | J33: 484927 | K33: 21 | L33: OPORTUNIDADE | Tratar descrição de LOG para Pedido de Compra | P33: 1 | Q33: 1 | R33: 1 | S33: =P33+Q33+R33 -> 3
A34: 34 | B34: 46329 | C34: Daniela Mochon | D34: Comercial | E34: C2603-13439 | F34: Entregue | G34: 1 | H34: BUG | I34: Funil | J34: 419044 | K34: 20 | L34: CONTA | Alterar Nome do Cliente após Subida de Nova Proposta | P34: 1 | Q34: 1 | R34: 1 | S34: =P34+Q34+R34 -> 3
A35: 35 | B35: 9511 | C35: Daniela Mochon | D35: Comercial | F35: Entregue | G35: 1 | H35: Melhoria | I35: Funil | J35: 387493 | K35: 20 | L35: OPORTUNIDADE | Desenvolver Exibição do Ano/Modelo na Oportunidade | P35: 1 | Q35: 1 | R35: 1 | S35: =P35+Q35+R35 -> 3
A36: 36 | B36: 46177 | C36: Daniela Mochon | D36: Comercial | E36: M2604-10920 | F36: Entregue | H36: Melhoria | I36: Funil | J36: 534334 | L36: LEAD | Melhoria no processo de Consulta SERASA + Log | S36: =P36+Q36+R36 -> #VALUE!
A37: 37 | B37: 46205 | C37: Daniela Mochon | D37: Comercial | F37: Entregue | G37: 3 | H37: Melhoria | I37: Funil | J37: 394012 | K37: 4 | L37: OPORTUNIDADE | Desenvolvimento de Subfases para oportunidades de Renovação | P37: 3 | Q37: 3 | R37: 3 | S37: =P37+Q37+R37 -> 9
A38: 38 | B38: 46115 | C38: Daniela Mochon | D38: Comercial | F38: Entregue | H38: Melhoria | I38: Funil | J38: 409101 | L38: OPORTUNIDADE | Desenvolver obrigatoriedade do Campo Subfase | S38: =P38+Q38+R38 -> #VALUE!
A39: 39 | B39: 46329 | C39: Daniela Mochon | D39: Comercial | F39: Entregue | G39: 2 | H39: Melhoria | I39: Funil | J39: 417288 | K39: 2 | L39: OPORTUNIDADE | Remover perfis do bloqueio de edição de campos na Oportunidade. | P39: 3 | Q39: 3 | R39: 3 | S39: =P39+Q39+R39 -> 9
A40: 40 | B40: 9488 | C40: Pedro Henrique | D40: Comercial | F40: Entregue | G40: 3 | H40: Melhoria | I40: Funil | J40: 383071 | K40: 4 | L40: OPORTUNIDADE | Liberar para edição de Oportunidades (Stage e Motivo) | P40: 3 | Q40: 3 | R40: 3 | S40: =P40+Q40+R40 -> 9
A41: 41 | B41: 46205 | C41: Daniela Mochon | D41: Comercial | F41: Entregue | G41: 1 | H41: BUG | I41: Funil | J41: 394013 | K41: 13 | L41: CONTRATO | Desenvolver remoção da trava de Cadastro SF x Assinatura | P41: 2 | Q41: 1 | R41: 2 | S41: =P41+Q41+R41 -> 5
A42: 42 | B42: 9574 | C42: Monique Evelin | D42: Comercial | F42: Entregue | G42: 3 | H42: Melhoria | I42: Funil | J42: 457607 | K42: 10 | L42: CONTRATO | Integração com Plataforma de Crédito "Tipo de Contrato" | P42: 3 | Q42: 2 | R42: 2 | S42: =P42+Q42+R42 -> 7
A43: 43 | B43: 46359 | C43: Pedro Henrique | D43: Comercial | F43: Entregue | G43: 1 | H43: Melhoria | I43: Funil | J43: 428396 | K43: 19 | L43: CONTRATO | Desenvolver JOB para que apenas 5 tipos de contratos gerem a Renovação | P43: 1 | Q43: 1 | R43: 1 | S43: =P43+Q43+R43 -> 3
A44: 44 | B44: 9551 | C44: Pedro Henrique | D44: Comercial | F44: Entregue | H44: BUG | I44: Funil | J44: 397404 | L44: OPORTUNIDADE | Desenvolver correção Motivo de Perda (Fechado Perdido) | S44: =P44+Q44+R44 -> #VALUE!
A45: 45 | B45: 9453 | C45: Aline Lucia Zarnicinski | D45: Comercial | F45: Entregue | H45: Melhoria | I45: Funil | J45: 370939 | L45: INTEGRAÇÃO | Adequações de Informações Enviadas ao SAP Commissions (Projeto SAPCOM – Nova Política) | S45: =P45+Q45+R45 -> #VALUE!
A46: 46 | B46: 9513 | C46: Daniela Mochon | D46: Comercial | F46: Entregue | G46: 3 | H46: Melhoria | I46: Funil | J46: 388244 | K46: 5 | L46: LEAD | Desenvolver Reencaminhamento de Leads “Lost” para SDR com Validação por Cidade | P46: 3 | Q46: 3 | R46: 3 | S46: =P46+Q46+R46 -> 9
A47: 47 | B47: 45700 | C47: Daniela Mochon | D47: Comercial | F47: Entregue | H47: Melhoria | I47: Funil | J47: 376474 | L47: OPORTUNIDADE | Preenchimento de Informações do LEAD (Vendedor / Revendedor / Gestor / Venda) | S47: =P47+Q47+R47 -> #VALUE!
A48: 48 | B48: 9569 | C48: Daniela Mochon | D48: Comercial | F48: Entregue | G48: 3 | H48: BUG | I48: Funil | J48: 434664 | K48: 10 | L48: LEAD | Investigar falha na conversão automática de Lead | P48: 3 | Q48: 2 | R48: 2 | S48: =P48+Q48+R48 -> 7
A49: 49 | B49: 9554 | C49: Cibele Thais | D49: Comercial | E49: C2602-34943 | F49: Entregue | G49: 1 | H49: BUG | I49: Funil | J49: 398780 | K49: 0 | L49: OPORTUNIDADE - Desenvolver correção de mudança indevida do status da Oportunidade | P49: 3 | Q49: 2 | R49: 2 | S49: =P49+Q49+R49 -> 7
A50: 50 | B50: 9551 | C50: Proativo | D50: Funil | F50: Entregue | H50: BUG | I50: Funil | J50: 397308 | L50: ACCOUNT | Desenvolver bloqueio na trigger quando o tipo de registro da Conta for Empresa | S50: =P50+Q50+R50 -> #VALUE!
A51: 51 | B51: 46359 | C51: Proativo | D51: Funil | F51: Entregue | H51: BUG | I51: Funil | J51: 422745 | L51: OPORTUNIDADE | Liberar a visualização do campo "Cadastro sincronizado SAP e Locavia" para o Perfil Atendimento Livre | S51: =P51+Q51+R51 -> #VALUE!
A52: 52 | B52: 46143 | C52: Proativo | D52: Funil | F52: Entregue | G52: 1 | H52: BUG | I52: Funil | J52: 385296 | K52: 0 | L52: OPORTUNIDADE | Correção de Cancelamento de Crédito e Validação de Múltiplas Chamadas | P52: 3 | Q52: 2 | R52: 2 | S52: =P52+Q52+R52 -> 7
A53: 53 | B53: 9511 | C53: Proativo | D53: Funil | F53: Entregue | G53: 1 | H53: Melhoria | I53: Funil | J53: 387519 | K53: 17 | L53: LEAD | Desenvolver Padronização do Cadastro de Cidades Atendidas pela UNIDAS | P53: 1 | Q53: 1 | R53: 1 | S53: =P53+Q53+R53 -> 3
A54: 54 | B54: 46297 | C54: Proativo | D54: Funil | F54: Entregue | H54: Melhoria | I54: Funil | J54: 394897 | L54: OPORTUNIDADE | Atualização e inclusão de motivos no campo “Motivo Fechado Perdido” | S54: =P54+Q54+R54 -> #VALUE!
A55: 55 | B55: 46114 | C55: Daniela Mochon | D55: Comercial | F55: Entregue | G55: 2 | H55: Melhoria | I55: Funil | J55: 393032 | K55: 2 | L55: RENOVAÇÃO | Desenvolver Integração de Pedidos de Renovação com Locavia | P55: 3 | Q55: 3 | R55: 3 | S55: =P55+Q55+R55 -> 9
A56: 56 | B56: 46002 | C56: Daniela Mochon | D56: Comercial | F56: Entregue | G56: 1 | H56: Melhoria | I56: Funil | J56: 369258 | K56: 0 | L56: OPORTUNIDADE | Fluxo de Renovação de Contratos (Atualização do Campo Categoria Contrato) | P56: 3 | Q56: 2 | R56: 2 | S56: =P56+Q56+R56 -> 7
A57: 57 | B57: 9525 | C57: Daniela Mochon | D57: Comercial | F57: Entregue | G57: 1 | H57: Melhoria | I57: Funil | J57: 391124 | K57: 20 | L57: OPORTUNIDADE | Desenvolver correção do preenchimento do campo IRIS_ValorKmRodado__c nas Oportunidades | P57: 1 | Q57: 1 | R57: 1 | S57: =P57+Q57+R57 -> 3
A58: 58 | B58: 9510 | C58: Pedro Henrique | D58: Comercial | E58: C2601-8878 | F58: Entregue | G58: 1 | H58: Melhoria | I58: Funil | J58: 387018 | K58: 20 | L58: OPORTUNIDADE | Liberação de edição do campo “Número do Contrato Master – Origem | P58: 1 | Q58: 1 | R58: 1 | S58: =P58+Q58+R58 -> 3
A59: 59 | B59: 9541 | C59: Pedro Henrique | D59: Comercial | F59: Entregue | G59: 3 | H59: Melhoria | I59: Funil | J59: 395870 | K59: 4 | L59: USER| Desenvolver liberação de edição de Oportunidades para IRIS_Gestor_Comercial_Livre | P59: 3 | Q59: 3 | R59: 3 | S59: =P59+Q59+R59 -> 9
A60: 60 | B60: 9617 | C60: Daniela Mochon | D60: Comercial | E60: C2604-33584 | F60: Entregue | G60: 3 | H60: BUG | I60: Funil | J60: 639777 | K60: 4 | L60: OPORTUNIDADE | Desenvolver correção de atualização de SubFase em Oportunidade de Renovação | P60: 3 | Q60: 3 | R60: 3 | S60: =P60+Q60+R60 -> 9
A61: 61 | B61: 9511 | C61: Proativo | D61: Funil | F61: Entregue | G61: 1 | H61: Melhoria | I61: Funil | J61: 387519 | K61: 17 | L61: LEAD | Desenvolver Padronização do Cadastro de Cidades Atendidas pela UNIDAS | P61: 1 | Q61: 1 | R61: 1 | S61: =P61+Q61+R61 -> 3
A62: 62 | B62: 46328 | C62: Daniela Mochon | D62: Comercial | F62: Entregue | H62: Melhoria | I62: Funil | J62: 395197 | L62: LEAD | Desenvolvimento de Correção Nº2 de Cadastro de Cidades via Integração | S62: =P62+Q62+R62 -> #VALUE!
A63: 63 | B63: 46143 | C63: Monique Evelin | D63: Crédito | F63: Entregue | G63: 1 | H63: BUG | I63: Funil | J63: 385296 | K63: 0 | L63: OPORTUNIDADE | Correção de Cancelamento de Crédito e Validação de Múltiplas Chamadas | P63: 3 | Q63: 2 | R63: 2 | S63: =P63+Q63+R63 -> 7
A64: 64 | B64: 46114 | C64: Daniela Mochon | D64: Comercial | F64: Entregue | H64: Melhoria | I64: Funil | J64: 393206 | L64: REPORT | Desenvolver Alteração no Botão de Relatório (Cotação Master) - Mário Sturlini | S64: =P64+Q64+R64 -> #VALUE!
A65: 65 | B65: 9510 | C65: Daniela Mochon | D65: Comercial | F65: Entregue | G65: 1 | H65: Melhoria | I65: Funil | J65: 387296 | K65: 22 | L65: OPORTUNIDADE | Correção da Data/Hora de Assinatura | P65: 1 | Q65: 1 | R65: 1 | S65: =P65+Q65+R65 -> 3
A66: 66 | B66: 46027.603 | C66: Daniela Mochon | D66: Comercial | F66: Entregue | G66: 1 | H66: Melhoria | I66: Funil | J66: 385296 | K66: 0 | L66: OPORTUNIDADE | Correção de Cancelamento de Crédito e Validação de Múltiplas Chamadas | P66: 3 | Q66: 2 | R66: 2 | S66: =P66+Q66+R66 -> 7
A67: 67 | B67: 46027.617 | C67: Daniela Mochon | D67: Comercial | F67: Entregue | G67: 3 | H67: Melhoria | I67: Funil | J67: 385303 | K67: 10 | L67: OPORTUNIDADE em QA | Correção de Dados da Oportunidade em Criação com Troca de Titularidade | P67: 3 | Q67: 2 | R67: 2 | S67: =P67+Q67+R67 -> 7
A68: 68 | B68: 46027.731 | C68: Daniela Mochon | D68: Comercial | F68: Entregue | G68: 3 | H68: Melhoria | I68: Funil | J68: 385378 | K68: 10 | L68: CONTRATO | Desenvolver na Integração para Ignorar Contrato Provisório no Preenchimento da Oportunidade | P68: 3 | Q68: 2 | R68: 2 | S68: =P68+Q68+R68 -> 7
A69: 69 | B69: 46035.408 | C69: Daniela Mochon | D69: Comercial | F69: Entregue | G69: 1 | H69: Melhoria | I69: Funil | J69: 387018 | K69: 20 | L69: OPORTUNIDADE | Liberação de edição do campo “Número do Contrato Master – Origem | P69: 1 | Q69: 1 | R69: 1 | S69: =P69+Q69+R69 -> 3
A70: 70 | B70: 46035.738 | C70: Daniela Mochon | D70: Comercial | F70: Entregue | G70: 1 | H70: Melhoria | I70: Funil | J70: 387296 | K70: 22 | L70: OPORTUNIDADE | Correção da Data/Hora de Assinatura | P70: 1 | Q70: 1 | R70: 1 | S70: =P70+Q70+R70 -> 3
A71: 71 | B71: 46036.51 | C71: Daniela Mochon | D71: Comercial | F71: Entregue | G71: 1 | H71: Melhoria | I71: Funil | J71: 387417 | K71: 21 | L71: QUOTE | Desenvolver Correção do Envio de Emplacamento no Pedido de Compra (GWM – SP) | P71: 1 | Q71: 1 | R71: 1 | S71: =P71+Q71+R71 -> 3
A72: 72 | B72: 46036.682 | C72: Daniela Mochon | D72: Comercial | F72: Entregue | G72: 1 | H72: Melhoria | I72: Funil | J72: 387519 | K72: 17 | L72: LEAD | Desenvolver Padronização do Cadastro de Cidades Atendidas pela UNIDAS | P72: 1 | Q72: 1 | R72: 1 | S72: =P72+Q72+R72 -> 3
A73: 73 | B73: 46036.705 | C73: Daniela Mochon | D73: Comercial | F73: Entregue | G73: 1 | H73: Melhoria | I73: Funil | J73: 387569 | K73: 21 | L73: ASSET | Ano do Produto Desatualizado | P73: 1 | Q73: 1 | R73: 1 | S73: =P73+Q73+R73 -> 3
A74: 74 | B74: 46041.365 | C74: Daniela Mochon | D74: Comercial | F74: Entregue | G74: 1 | H74: Melhoria | I74: Funil | J74: 388456 | K74: 13 | L74: CONTRATO | Desativação da ValidationRule de Assinatura do Contrato | P74: 2 | Q74: 1 | R74: 2 | S74: =P74+Q74+R74 -> 5
A75: 75 | B75: 46042.864 | C75: Daniela Mochon | D75: Comercial | F75: Entregue | G75: 3 | H75: Melhoria | I75: Funil | J75: 389140 | K75: 5 | L75: LEAD | Desenvolver Fluxo de Consulta com Pré-Score | P75: 3 | Q75: 3 | R75: 3 | S75: =P75+Q75+R75 -> 9
A76: 76 | B76: 46050.723 | C76: Daniela Mochon | D76: Comercial | F76: Entregue | G76: 1 | H76: Melhoria | I76: Funil | J76: 391124 | K76: 20 | L76: OPORTUNIDADE | Desenvolver correção do preenchimento do campo IRIS_ValorKmRodado__c nas Oportunidades | P76: 1 | Q76: 1 | R76: 1 | S76: =P76+Q76+R76 -> 3
A77: 77 | B77: 46057.574 | C77: Daniela Mochon | D77: Comercial | F77: Entregue | G77: 2 | H77: Melhoria | I77: Funil | J77: 393032 | K77: 2 | L77: RENOVAÇÃO | Desenvolver Integração de Pedidos de Renovação com Locavia | P77: 3 | Q77: 3 | R77: 3 | S77: =P77+Q77+R77 -> 9
A78: 78 | B78: 46063.59 | C78: Daniela Mochon | D78: Comercial | F78: Entregue | H78: Melhoria | I78: Funil | J78: 394897 | L78: OPORTUNIDADE | Atualização e inclusão de motivos no campo “Motivo Fechado Perdido” | S78: =P78+Q78+R78 -> #VALUE!
A79: 79 | B79: 46064.43 | C79: Daniela Mochon | D79: Comercial | F79: Entregue | H79: Melhoria | I79: Funil | J79: 395197 | L79: LEAD | Desenvolvimento de Correção Nº2 de Cadastro de Cidades via Integração | S79: =P79+Q79+R79 -> #VALUE!
A80: 80 | B80: 46064.432 | C80: Daniela Mochon | D80: Comercial | F80: Entregue | H80: Melhoria | I80: Funil | J80: 395200 | L80: PRODUTO | Voltar Flow e da UF de Emplacamento | S80: =P80+Q80+R80 -> #VALUE!
A81: 81 | B81: 46066.658 | C81: Daniela Mochon | D81: Comercial | F81: Entregue | G81: 3 | H81: Melhoria | I81: Funil | J81: 395870 | K81: 4 | L81: USER| Desenvolver liberação de edição de Oportunidades para IRIS_Gestor_Comercial_Livre | P81: 3 | Q81: 3 | R81: 3 | S81: =P81+Q81+R81 -> 9
A82: 82 | B82: 46076.603 | C82: Daniela Mochon | D82: Comercial | F82: Entregue | H82: Melhoria | I82: Funil | J82: 397308 | L82: ACCOUNT | Desenvolver bloqueio na trigger quando o tipo de registro da Conta for Empresa | S82: =P82+Q82+R82 -> #VALUE!
A83: 83 | B83: 46076.722 | C83: Daniela Mochon | D83: Comercial | F83: Entregue | H83: Melhoria | I83: Funil | J83: 397404 | L83: OPORTUNIDADE | Desenvolver correção Motivo de Perda (Fechado Perdido) | S83: =P83+Q83+R83 -> #VALUE!
A84: 84 | B84: 46077.404 | C84: Daniela Mochon | D84: Comercial | F84: Entregue | G84: 1 | H84: Melhoria | I84: Funil | J84: 397510 | K84: 0 | L84: PRODUTO | Criação do campo “Migração AX” em Product2 e Asset com visibilidade controlada | P84: 3 | Q84: 2 | R84: 2 | S84: =P84+Q84+R84 -> 7
A85: 85 | B85: 46079.674 | C85: Daniela Mochon | D85: Comercial | F85: Entregue | G85: 1 | H85: Melhoria | I85: Funil | J85: 398780 | K85: 0 | L85: OPORTUNIDADE - Desenvolver correção de mudança indevida do status da Oportunidade | P85: 3 | Q85: 2 | R85: 2 | S85: =P85+Q85+R85 -> 7
A86: 86 | B86: 46085.675 | C86: Daniela Mochon | D86: Comercial | F86: Entregue | H86: Melhoria | I86: Funil | J86: 409101 | L86: OPORTUNIDADE | Desenvolver obrigatoriedade do Campo Subfase | S86: =P86+Q86+R86 -> #VALUE!
A87: 87 | B87: 46092.77 | C87: Daniela Mochon | D87: Comercial | F87: Entregue | G87: 1 | H87: Melhoria | I87: Funil | J87: 419044 | K87: 20 | L87: CONTA | Alterar Nome do Cliente após Subida de Nova Proposta | P87: 1 | Q87: 1 | R87: 1 | S87: =P87+Q87+R87 -> 3
A88: 88 | B88: 46093.578 | C88: Daniela Mochon | D88: Comercial | F88: Entregue | H88: Melhoria | I88: Funil | J88: 422745 | L88: OPORTUNIDADE | Liberar a visualização do campo "Cadastro sincronizado SAP e Locavia" para o Perfil Atendimento Livre | S88: =P88+Q88+R88 -> #VALUE!
A89: 89 | B89: 46093.797 | C89: Daniela Mochon | D89: Comercial | F89: Entregue | G89: 1 | H89: Melhoria | I89: Funil | J89: 428396 | K89: 19 | L89: CONTRATO | Desenvolver JOB para que apenas 5 tipos de contratos gerem a Renovação | P89: 1 | Q89: 1 | R89: 1 | S89: =P89+Q89+R89 -> 3
A90: 90 | B90: 46094.438 | C90: Daniela Mochon | D90: Comercial | F90: Entregue | G90: 3 | H90: Melhoria | I90: Funil | J90: 434664 | K90: 10 | L90: LEAD | Investigar falha na conversão automática de Lead | P90: 3 | Q90: 2 | R90: 2 | S90: =P90+Q90+R90 -> 7
A91: 91 | B91: 46099.616 | C91: Daniela Mochon | D91: Comercial | F91: Entregue | G91: 3 | H91: Melhoria | I91: Funil | J91: 457607 | K91: 10 | L91: CONTRATO | Integração com Plataforma de Crédito "Tipo de Contrato" | P91: 3 | Q91: 2 | R91: 2 | S91: =P91+Q91+R91 -> 7
A92: 92 | B92: 46060.914 | C92: Daniela Mochon | D92: Comercial | F92: Entregue | G92: 3 | H92: Melhoria | I92: Funil | J92: 394012 | K92: 4 | L92: OPORTUNIDADE | Desenvolvimento de Subfases para oportunidades de Renovação | P92: 3 | Q92: 3 | R92: 3 | S92: =P92+Q92+R92 -> 9
A93: 93 | B93: 46060.947 | C93: Daniela Mochon | D93: Comercial | F93: Entregue | G93: 1 | H93: Melhoria | I93: Funil | J93: 394013 | K93: 13 | L93: CONTRATO | Desenvolver remoção da trava de Cadastro SF x Assinatura | P93: 2 | Q93: 1 | R93: 2 | S93: =P93+Q93+R93 -> 5
A94: 94 | B94: 46104.602 | C94: Daniela Mochon | D94: Comercial | F94: Entregue | G94: 1 | H94: Melhoria | I94: Funil | J94: 484927 | K94: 21 | L94: OPORTUNIDADE | Tratar descrição de LOG para Pedido de Compra | P94: 1 | Q94: 1 | R94: 1 | S94: =P94+Q94+R94 -> 3
A95: 95 | B95: 46118.658 | C95: Daniela Mochon | D95: Comercial | F95: Entregue | H95: Melhoria | I95: Funil | J95: 534334 | L95: LEAD | Melhoria no processo de Consulta SERASA + Log | S95: =P95+Q95+R95 -> #VALUE!
A96: 96 | B96: 46120.543 | C96: Daniela Mochon | D96: Comercial | F96: Entregue | G96: 1 | H96: Melhoria | I96: Funil | J96: 539549 | K96: 12 | L96: CONTA | Desenvolver Alteração Nome do Cliente após Subida de Nova Proposta | P96: 2 | Q96: 1 | R96: 2 | S96: =P96+Q96+R96 -> 5
A97: 97 | B97: 46092.592 | C97: Daniela Mochon | D97: Comercial | F97: Entregue | G97: 2 | H97: Melhoria | I97: Funil | J97: 417288 | K97: 2 | L97: OPORTUNIDADE | Remover perfis do bloqueio de edição de campos na Oportunidade. | P97: 3 | Q97: 3 | R97: 3 | S97: =P97+Q97+R97 -> 9
A98: 98 | B98: 46043.472 | C98: Daniela Mochon | D98: Comercial | F98: Entregue | G98: 2 | H98: Melhoria | I98: Funil | J98: 389294 | K98: 2 | L98: CONTRATO | Tornar FirstName não obrigatório na criação de Contrato | P98: 3 | Q98: 3 | R98: 3 | S98: =P98+Q98+R98 -> 9
A99: 99 | B99: 46036.66 | C99: Daniela Mochon | D99: Comercial | F99: Entregue | G99: 1 | H99: Melhoria | I99: Funil | J99: 387493 | K99: 20 | L99: OPORTUNIDADE | Desenvolver Exibição do Ano/Modelo na Oportunidade | P99: 1 | Q99: 1 | R99: 1 | S99: =P99+Q99+R99 -> 3
A100: 100 | B100: 46038.58 | C100: Daniela Mochon | D100: Comercial | F100: Entregue | G100: 3 | H100: Melhoria | I100: Funil | J100: 388244 | K100: 5 | L100: LEAD | Desenvolver Reencaminhamento de Leads “Lost” para SDR com Validação por Cidade | P100: 3 | Q100: 3 | R100: 3 | S100: =P100+Q100+R100 -> 9
...

Sheet Pró ativos
B1: ID | C1: Data da Inserção | D1: Solicitante | E1: Chamado | F1: Status | G1: Avaliação área de Negocio | H1: Classificação área | I1: Resumo Melhoria | J1: Descrição | K1: OBS | L1: Tamanho | M1: Comitê de TI | N1: Squad On Going | O1: Nº Azure | P1: Gravidade | Q1: Urgência | R1: Tendência | S1: Resultado GUT | T1: Prioridade | U1: Historia

Sheet Debito Tecnico
A1: ID | B1: Data da Inserção | C1: Solicitante | D1: Área | E1: Chamado | F1: Squad | G1: Status | H1: Avaliação área de Negocio | I1: Classificação área | J1: Resumo Melhoria | K1: Descrição | L1: OBS | M1: Tamanho | N1: Comitê de TI | O1: Squad On Going | P1: Nº Azure | Q1: Gravidade | R1: Urgência | S1: Tendência | T1: Resultado GUT | U1: Prioridade | V1: Historia
N2: FALSE | O2: FALSE
N3: FALSE | O3: FALSE
N4: FALSE | O4: FALSE

Sheet Status
A1: Status
A2: Aguardando Capacity
A3: Aguardando Desenvolvimento da História
A4: Aguardando Refinamento de Negócio
A5: Aguardando Refinamento TI
A6: Backlog
A7: Bloqueado
A8: Cancelado
A9: Em Análise Técnica TI
A10: Pronto para Desenvolvimento
A11: Em Desenvolvimento
A12: Entregue
... A21: QA
